Workbook
Name Datos_Empleados: Datos_Empleados!$A$1:$J$9
Name Datos_Ventas_Completos: Datos_Ventas_Completos!$A$1:$X$101
Name Satisfaccion_Cliente: Datos_Ventas_Completos!$I$2
Name SegmentaciónDeDatos_Canal_Venta: #N/A
Name SegmentaciónDeDatos_Categoria: #N/A
Name SegmentaciónDeDatos_Fecha: #N/A
Name SegmentaciónDeDatos_Region: #N/A
Name Ventas_Actuales: Datos_Ventas_Completos!$M$4

Sheet Hoja1
A1: Vendedor | B1: (Todas)
A2: Metodo_Pago | B2: (Todas)
B4: Etiquetas de columna
B5: Q1 | Z5: Suma de Ticket_Promedio2 Q1 | AA5: Suma de Margen_Promedio2 Q1 | AB5: Suma de Rentabilidad_Pct Q1 | AC5: Cuenta de ID_Transaccion Q1 | AD5: Suma de Ingresos_Totales Q1 | AE5: Suma de Satisfaccion_Cliente Q1 | AF5: Suma de Margen_Promedio Q1 | AG5: Suma de Ticket_Promedio Q1 | AH5: Total Suma de Ticket_Promedio2 | AI5: Total Suma de Margen_Promedio2 | AJ5: Total Suma de Rentabilidad_Pct | AK5: Total Cuenta de ID_Transaccion | AL5: Total Suma de Ingresos_Totales | AM5: Total Suma de Satisfaccion_Cliente | AN5: Total Suma de Margen_Promedio | AO5: Total Suma de Ticket_Promedio
B6: Estandar | J6: Premium | R6: Riesgo
A7: Etiquetas de fila | B7: Suma de Ticket_Promedio2 | C7: Suma de Margen_Promedio2 | D7: Suma de Rentabilidad_Pct | E7: Cuenta de ID_Transaccion | F7: Suma de Ingresos_Totales | G7: Suma de Satisfaccion_Cliente | H7: Suma de Margen_Promedio | I7: Suma de Ticket_Promedio | J7: Suma de Ticket_Promedio2 | K7: Suma de Margen_Promedio2 | L7: Suma de Rentabilidad_Pct | M7: Cuenta de ID_Transaccion | N7: Suma de Ingresos_Totales | O7: Suma de Satisfaccion_Cliente | P7: Suma de Margen_Promedio | Q7: Suma de Ticket_Promedio | R7: Suma de Ticket_Promedio2 | S7: Suma de Margen_Promedio2 | T7: Suma de Rentabilidad_Pct | U7: Cuenta de ID_Transaccion | V7: Suma de Ingresos_Totales | W7: Suma de Satisfaccion_Cliente | X7: Suma de Margen_Promedio | Y7: Suma de Ticket_Promedio
A8: Este | B8: 758.51111 | C8: 0.34060001 | D8: 1.2855907 | E8: 4 | F8: 6826.6 | G8: 16.8 | H8: 0.34060001 | I8: 758.51111 | J8: 699.44 | K8: 0.31533298 | L8: 2.1726943 | M8: 7 | N8: 13988.8 | O8: 33.4 | P8: 0.31533298 | Q8: 699.44 | R8: 918.22875 | S8: 0.32446054 | T8: 3.5411135 | U8: 11 | V8: 36729.15 | W8: 40.8 | X8: 0.32446054 | Y8: 918.22875 | Z8: 833.97899 | AA8: 0.32415633 | AB8: 6.9993986 | AC8: 22 | AD8: 57544.55 | AE8: 91 | AF8: 0.32415633 | AG8: 833.97899 | AH8: 833.97899 | AI8: 0.32415633 | AJ8: 6.9993986 | AK8: 22 | AL8: 57544.55 | AM8: 91 | AN8: 0.32415633 | AO8: 833.97899
A9: Distribuidor | B9: 384.2 | C9: 0.33097345 | D9: 0.33097345 | E9: 1 | F9: 1536.8 | G9: 4.1 | H9: 0.33097345 | I9: 384.2 | J9: 697.73846 | K9: 0.29198068 | L9: 1.4548061 | M9: 5 | N9: 9070.6 | O9: 23.7 | P9: 0.29198068 | Q9: 697.73846 | R9: 970.90385 | S9: 0.32871115 | T9: 1.2914819 | U9: 4 | V9: 12621.75 | W9: 14.4 | X9: 0.32871115 | Y9: 970.90385 | Z9: 774.305 | AA9: 0.31451818 | AB9: 3.0772614 | AC9: 10 | AD9: 23229.15 | AE9: 42.2 | AF9: 0.31451818 | AG9: 774.305 | AH9: 774.305 | AI9: 0.31451818 | AJ9: 3.0772614 | AK9: 10 | AL9: 23229.15 | AM9: 42.2 | AN9: 0.31451818 | AO9: 774.305
A10: Laptops | B10: #DIV/0! | C10: #DIV/0! | H10: #DIV/0! | I10: #DIV/0! | J10: 1069.2 | K10: 0.31878507 | L10: 0.31878507 | M10: 1 | N10: 2138.4 | O10: 4.7 | P10: 0.31878507 | Q10: 1069.2 | R10: 1016.4375 | S10: 0.36253336 | T10: 0.68279082 | U10: 2 | V10: 4065.75 | W10: 7 | X10: 0.36253336 | Y10: 1016.4375 | Z10: 1034.025 | AA10: 0.34745453 | AB10: 1.0015759 | AC10: 3 | AD10: 6204.15 | AE10: 11.7 | AF10: 0.34745453 | AG10: 1034.025 | AH10: 1034.025 | AI10: 0.34745453 | AJ10: 1.0015759 | AK10: 3 | AL10: 6204.15 | AM10: 11.7 | AN10: 0.34745453 | AO10: 1034.025
A11: Smartphones | B11: #DIV/0! | C11: #DIV/0! | H11: #DIV/0! | I11: #DIV/0! | J11: 754.30714 | K11: 0.28420026 | L11: 0.59850385 | M11: 2 | N11: 5280.15 | O11: 9.4 | P11: 0.28420026 | Q11: 754.30714 | R11: 950.66667 | S11: 0.31263908 | T11: 0.60869104 | U11: 2 | V11: 8556 | W11: 7.4 | X11: 0.31263908 | Y11: 950.66667 | Z11: 864.75937 | AA11: 0.30178626 | AB11: 1.2071949 | AC11: 4 | AD11: 13836.15 | AE11: 16.8 | AF11: 0.30178626 | AG11: 864.75937 | AH11: 864.75937 | AI11: 0.30178626 | AJ11: 1.2071949 | AK11: 4 | AL11: 13836.15 | AM11: 16.8 | AN11: 0.30178626 | AO11: 864.75937
A12: Tablets | B12: 384.2 | C12: 0.33097345 | D12: 0.33097345 | E12: 1 | F12: 1536.8 | G12: 4.1 | H12: 0.33097345 | I12: 384.2 | J12: 413.0125 | K12: 0.28215248 | L12: 0.53751716 | M12: 2 | N12: 1652.05 | O12: 9.6 | P12: 0.28215248 | Q12: 413.0125 | R12: #DIV/0! | S12: #DIV/0! | X12: #DIV/0! | Y12: #DIV/0! | Z12: 398.60625 | AA12: 0.30568073 | AB12: 0.86849061 | AC12: 3 | AD12: 3188.85 | AE12: 13.7 | AF12: 0.30568073 | AG12: 398.60625 | AH12: 398.60625 | AI12: 0.30568073 | AJ12: 0.86849061 | AK12: 3 | AL12: 3188.85 | AM12: 13.7 | AN12: 0.30568073 | AO12: 398.60625
A13: Online | B13: 1020.6 | C13: 0.33726239 | D13: 0.60279053 | E13: 2 | F13: 3061.8 | G13: 8.6 | H13: 0.33726239 | I13: 1020.6 | J13: 702.6 | K13: 0.35840145 | L13: 0.71788825 | M13: 2 | N13: 4918.2 | O13: 9.7 | P13: 0.35840145 | Q13: 702.6 | R13: 973.78333 | S13: 0.3340847 | T13: 1.6687246 | U13: 5 | V13: 17528.1 | W13: 18.6 | X13: 0.3340847 | Y13: 973.78333 | Z13: 911.00357 | AA13: 0.33915462 | AB13: 2.9894034 | AC13: 9 | AD13: 25508.1 | AE13: 36.9 | AF13: 0.33915462 | AG13: 911.00357 | AH13: 911.00357 | AI13: 0.33915462 | AJ13: 2.9894034 | AK13: 9 | AL13: 25508.1 | AM13: 36.9 | AN13: 0.33915462 | AO13: 911.00357
A14: Laptops | B14: 1052.1 | C14: 0.39717232 | D14: 0.39717232 | E14: 1 | F14: 2104.2 | G14: 4.1 | H14: 0.39717232 | I14: 1052.1 | J14: 1210 | K14: 0.35780441 | L14: 0.35780441 | M14: 1 | N14: 3630 | O14: 4.9 | P14: 0.35780441 | Q14: 1210 | R14: 1238.05 | S14: 0.32212431 | T14: 0.9504215 | U14: 3 | V14: 12380.5 | W14: 10.9 | X14: 0.32212431 | Y14: 1238.05 | Z14: 1207.6467 | AA14: 0.3379918 | AB14: 1.7053982 | AC14: 5 | AD14: 18114.7 | AE14: 19.9 | AF14: 0.3379918 | AG14: 1207.6467 | AH14: 1207.6467 | AI14: 0.3379918 | AJ14: 1.7053982 | AK14: 5 | AL14: 18114.7 | AM14: 19.9 | AN14: 0.3379918 | AO14: 1207.6467
A15: Smartphones | B15: 957.6 | C15: 0.20561821 | D15: 0.20561821 | E15: 1 | F15: 957.6 | G15: 4.5 | H15: 0.20561821 | I15: 957.6 | J15: #DIV/0! | K15: #DIV/0! | P15: #DIV/0! | Q15: #DIV/0! | R15: 747.9 | S15: 0.38193943 | T15: 0.38193943 | U15: 1 | V15: 2991.6 | W15: 3.8 | X15: 0.38193943 | Y15: 747.9 | Z15: 789.84 | AA15: 0.33918515 | AB15: 0.58755764 | AC15: 2 | AD15: 3949.2 | AE15: 8.3 | AF15: 0.33918515 | AG15: 789.84 | AH15: 789.84 | AI15: 0.33918515 | AJ15: 0.58755764 | AK15: 2 | AL15: 3949.2 | AM15: 8.3 | AN15: 0.33918515 | AO15: 789.84
A16: Tablets | B16: #DIV/0! | C16: #DIV/0! | H16: #DIV/0! | I16: #DIV/0! | J16: 322.05 | K16: 0.36008384 | L16: 0.36008384 | M16: 1 | N16: 1288.2 | O16: 4.8 | P16: 0.36008384 | Q16: 322.05 | R16: 539 | S16: 0.33636364 | T16: 0.33636364 | U16: 1 | V16: 2156 | W16: 3.9 | X16: 0.33636364 | Y16: 539 | Z16: 430.525 | AA16: 0.34523547 | AB16: 0.69644747 | AC16: 2 | AD16: 3444.2 | AE16: 8.7 | AF16: 0.34523547 | AG16: 430.525 | AH16: 430.525 | AI16: 0.34523547 | AJ16: 0.69644747 | AK16: 2 | AL16: 3444.2 | AM16: 8.7 | AN16: 0.34523547 | AO16: 430.525
A17: Tienda | B17: 1114 | C17: 0.35182675 | D17: 0.35182675 | E17: 1 | F17: 2228 | G17: 4.1 | H17: 0.35182675 | I17: 1114 | J17: #DIV/0! | K17: #DIV/0! | P17: #DIV/0! | Q17: #DIV/0! | R17: 731.03333 | S17: 0.29066618 | T17: 0.58090711 | U17: 2 | V17: 6579.3 | W17: 7.8 | X17: 0.29066618 | Y17: 731.03333 | Z17: 800.66364 | AA17: 0.30613809 | AB17: 0.93273387 | AC17: 3 | AD17: 8807.3 | AE17: 11.9 | AF17: 0.30613809 | AG17: 800.66364 | AH17: 800.66364 | AI17: 0.30613809 | AJ17: 0.93273387 | AK17: 3 | AL17: 8807.3 | AM17: 11.9 | AN17: 0.30613809 | AO17: 800.66364
A18: Laptops | B18: 1114 | C18: 0.35182675 | D18: 0.35182675 | E18: 1 | F18: 2228 | G18: 4.1 | H18: 0.35182675 | I18: 1114 | J18: #DIV/0! | K18: #DIV/0! | P18: #DIV/0! | Q18: #DIV/0! | R18: #DIV/0! | S18: #DIV/0! | X18: #DIV/0! | Y18: #DIV/0! | Z18: 1114 | AA18: 0.35182675 | AB18: 0.35182675 | AC18: 1 | AD18: 2228 | AE18: 4.1 | AF18: 0.35182675 | AG18: 1114 | AH18: 1114 | AI18: 0.35182675 | AJ18: 0.35182675 | AK18: 1 | AL18: 2228 | AM18: 4.1 | AN18: 0.35182675 | AO18: 1114
A19: Tablets | B19: #DIV/0! | C19: #DIV/0! | H19: #DIV/0! | I19: #DIV/0! | J19: #DIV/0! | K19: #DIV/0! | P19: #DIV/0! | Q19: #DIV/0! | R19: 731.03333 | S19: 0.29066618 | T19: 0.58090711 | U19: 2 | V19: 6579.3 | W19: 7.8 | X19: 0.29066618 | Y19: 731.03333 | Z19: 731.03333 | AA19: 0.29066618 | AB19: 0.58090711 | AC19: 2 | AD19: 6579.3 | AE19: 7.8 | AF19: 0.29066618 | AG19: 731.03333 | AH19: 731.03333 | AI19: 0.29066618 | AJ19: 0.58090711 | AK19: 2 | AL19: 6579.3 | AM19: 7.8 | AN19: 0.29066618 | AO19: 731.03333
A20: Norte | B20: 1136.4656 | C20: 0.28034614 | D20: 1.6834015 | E20: 6 | F20: 18183.45 | G20: 25.9 | H20: 0.28034614 | I20: 1136.4656 | J20: 770.87 | K20: 0.25735857 | L20: 1.5520957 | M20: 6 | N20: 11563.05 | O20: 29 | P20: 0.25735857 | Q20: 770.87 | R20: 817.58333 | S20: 0.2875277 | T20: 4.1799818 | U20: 14 | V20: 34338.5 | W20: 49.8 | X20: 0.2875277 | Y20: 817.58333 | Z20: 877.87671 | AA20: 0.2800465 | AB20: 7.415479 | AC20: 26 | AD20: 64085 | AE20: 104.7 | AF20: 0.2800465 | AG20: 877.87671 | AH20: 877.87671 | AI20: 0.2800465 | AJ20: 7.415479 | AK20: 26 | AL20: 64085 | AM20: 104.7 | AN20: 0.2800465 | AO20: 877.87671
A21: Distribuidor | B21: 1225.8 | C21: 0.29446484 | D21: 0.29446484 | E21: 1 | F21: 2451.6 | G21: 4.2 | H21: 0.29446484 | I21: 1225.8 | J21: 1027.1937 | K21: 0.24601128 | L21: 0.69866783 | M21: 3 | N21: 8217.55 | O21: 14.7 | P21: 0.24601128 | Q21: 1027.1937 | R21: 779.825 | S21: 0.29567852 | T21: 2.1282334 | U21: 7 | V21: 15596.5 | W21: 24.5 | X21: 0.29567852 | Y21: 779.825 | Z21: 875.52167 | AA21: 0.28002619 | AB21: 3.1213661 | AC21: 11 | AD21: 26265.65 | AE21: 43.4 | AF21: 0.28002619 | AG21: 875.52167 | AH21: 875.52167 | AI21: 0.28002619 | AJ21: 3.1213661 | AK21: 11 | AL21: 26265.65 | AM21: 43.4 | AN21: 0.28002619 | AO21: 875.52167
A22: Laptops | B22: 1225.8 | C22: 0.29446484 | D22: 0.29446484 | E22: 1 | F22: 2451.6 | G22: 4.2 | H22: 0.29446484 | I22: 1225.8 | J22: 1122.85 | K22: 0.23305577 | L22: 0.23305577 | M22: 1 | N22: 3368.55 | O22: 5 | P22: 0.23305577 | Q22: 1122.85 | R22: 1120.45 | S22: 0.3548128 | T22: 0.70898833 | U22: 2 | V22: 4481.8 | W22: 7.8 | X22: 0.3548128 | Y22: 1120.45 | Z22: 1144.6611 | AA22: 0.3006392 | AB22: 1.2365089 | AC22: 4 | AD22: 10301.95 | AE22: 17 | AF22: 0.3006392 | AG22: 1144.6611 | AH22: 1144.6611 | AI22: 0.3006392 | AJ22: 1.2365089 | AK22: 4 | AL22: 10301.95 | AM22: 17 | AN22: 0.3006392 | AO22: 1144.6611
A23: Smartphones | B23: #DIV/0! | C23: #DIV/0! | H23: #DIV/0! | I23: #DIV/0! | J23: 1020 | K23: 0.26532598 | L23: 0.26532598 | M23: 1 | N23: 4080 | O23: 5 | P23: 0.26532598 | Q23: 1020 | R23: 740.9 | S23: 0.2563785 | T23: 0.79712474 | U23: 3 | V23: 8890.8 | W23: 10.2 | X23: 0.2563785 | Y23: 740.9 | Z23: 810.675 | AA23: 0.25919296 | AB23: 1.0624507 | AC23: 4 | AD23: 12970.8 | AE23: 15.2 | AF23: 0.25919296 | AG23: 810.675 | AH23: 810.675 | AI23: 0.25919296 | AJ23: 1.0624507 | AK23: 4 | AL23: 12970.8 | AM23: 15.2 | AN23: 0.25919296 | AO23: 810.675
A24: Tablets | B24: #DIV/0! | C24: #DIV/0! | H24: #DIV/0! | I24: #DIV/0! | J24: 769 | K24: 0.20028609 | L24: 0.20028609 | M24: 1 | N24: 769 | O24: 4.7 | P24: 0.20028609 | Q24: 769 | R24: 555.975 | S24: 0.33362112 | T24: 0.62212036 | U24: 2 | V24: 2223.9 | W24: 6.5 | X24: 0.33362112 | Y24: 555.975 | Z24: 598.58 | AA24: 0.29936182 | AB24: 0.82240645 | AC24: 3 | AD24: 2992.9 | AE24: 11.2 | AF24: 0.29936182 | AG24: 598.58 | AH24: 598.58 | AI24: 0.29936182 | AJ24: 0.82240645 | AK24: 3 | AL24: 2992.9 | AM24: 11.2 | AN24: 0.29936182 | AO24: 598.58
A25: Online | B25: 1178.585 | C25: 0.27783486 | D25: 0.81592072 | E25: 3 | F25: 11785.85 | G25: 13.3 | H25: 0.27783486 | I25: 1178.585 | J25: 528 | K25: 0.26465909 | L25: 0.26465909 | M25: 1 | N25: 1056 | O25: 4.8 | P25: 0.26465909 | Q25: 528 | R25: 665.625 | S25: 0.31750235 | T25: 0.63574491 | U25: 2 | V25: 2662.5 | W25: 7.7 | X25: 0.31750235 | Y25: 665.625 | Z25: 969.02188 | AA25: 0.2837494 | AB25: 1.7163247 | AC25: 6 | AD25: 15504.35 | AE25: 25.8 | AF25: 0.2837494 | AG25: 969.02188 | AH25: 969.02188 | AI25: 0.2837494 | AJ25: 1.7163247 | AK25: 6 | AL25: 15504.35 | AM25: 25.8 | AN25: 0.2837494 | AO25: 969.02188
A26: Laptops | B26: 1210.4667 | C26: 0.27910907 | D26: 0.55365413 | E26: 2 | F26: 10894.2 | G26: 8.9 | H26: 0.27910907 | I26: 1210.4667 | J26: #DIV/0! | K26: #DIV/0! | P26: #DIV/0! | Q26: #DIV/0! | R26: 956 | S26: 0.31702406 | T26: 0.31702406 | U26: 1 | V26: 1912 | W26: 3.7 | X26: 0.31702406 | Y26: 956 | Z26: 1164.2 | AA26: 0.28476988 | AB26: 0.87067819 | AC26: 3 | AD26: 12806.2 | AE26: 12.6 | AF26: 0.28476988 | AG26: 1164.2 | AH26: 1164.2 | AI26: 0.28476988 | AJ26: 0.87067819 | AK26: 3 | AL26: 12806.2 | AM26: 12.6 | AN26: 0.28476988 | AO26: 1164.2
A27: Smartphones | B27: 891.65 | C27: 0.26226658 | D27: 0.26226658 | E27: 1 | F27: 891.65 | G27: 4.4 | H27: 0.26226658 | I27: 891.65 | J27: #DIV/0! | K27: #DIV/0! | P27: #DIV/0! | Q27: #DIV/0! | R27: #DIV/0! | S27: #DIV/0! | X27: #DIV/0! | Y27: #DIV/0! | Z27: 891.65 | AA27: 0.26226658 | AB27: 0.26226658 | AC27: 1 | AD27: 891.65 | AE27: 4.4 | AF27: 0.26226658 | AG27: 891.65 | AH27: 891.65 | AI27: 0.26226658 | AJ27: 0.26226658 | AK27: 1 | AL27: 891.65 | AM27: 4.4 | AN27: 0.26226658 | AO27: 891.65
A28: Tablets | B28: #DIV/0! | C28: #DIV/0! | H28: #DIV/0! | I28: #DIV/0! | J28: 528 | K28: 0.26465909 | L28: 0.26465909 | M28: 1 | N28: 1056 | O28: 4.8 | P28: 0.26465909 | Q28: 528 | R28: 375.25 | S28: 0.31872085 | T28: 0.31872085 | U28: 1 | V28: 750.5 | W28: 4 | X28: 0.31872085 | Y28: 375.25 | Z28: 451.625 | AA28: 0.28711874 | AB28: 0.58337994 | AC28: 2 | AD28: 1806.5 | AE28: 8.8 | AF28: 0.28711874 | AG28: 451.625 | AH28: 451.625 | AI28: 0.28711874 | AJ28: 0.58337994 | AK28: 2 | AL28: 1806.5 | AM28: 8.8 | AN28: 0.28711874 | AO28: 451.625
A29: Tienda | B29: 986.5 | C29: 0.27907501 | D29: 0.57301596 | E29: 2 | F29: 3946 | G29: 8.4 | H29: 0.27907501 | I29: 986.5 | J29: 457.9 | K29: 0.29471937 | L29: 0.58876875 | M29: 2 | N29: 2289.5 | O29: 9.5 | P29: 0.29471937 | Q29: 457.9 | R29: 893.30556 | S29: 0.27465842 | T29: 1.4160035 | U29: 5 | V29: 16079.5 | W29: 17.6 | X29: 0.27465842 | Y29: 893.30556 | Z29: 826.48148 | AA29: 0.27749765 | AB29: 2.5777882 | AC29: 9 | AD29: 22315 | AE29: 35.5 | AF29: 0.27749765 | AG29: 826.48148 | AH29: 826.48148 | AI29: 0.27749765 | AJ29: 2.5777882 | AK29: 9 | AL29: 22315 | AM29: 35.5 | AN29: 0.27749765 | AO29: 826.48148
A30: Laptops | B30: 1158 | C30: 0.24375216 | D30: 0.24375216 | E30: 1 | F30: 2316 | G30: 4.3 | H30: 0.24375216 | I30: 1158 | J30: 909.5 | K30: 0.29275426 | L30: 0.29275426 | M30: 1 | N30: 909.5 | O30: 4.9 | P30: 0.29275426 | Q30: 909.5 | R30: 808.45 | S30: 0.21650566 | T30: 0.21650566 | U30: 1 | V30: 4042.25 | W30: 3.2 | X30: 0.21650566 | Y30: 808.45 | Z30: 908.46875 | AA30: 0.23473014 | AB30: 0.75301208 | AC30: 3 | AD30: 7267.75 | AE30: 12.4 | AF30: 0.23473014 | AG30: 908.46875 | AH30: 908.46875 | AI30: 0.23473014 | AJ30: 0.75301208 | AK30: 3 | AL30: 7267.75 | AM30: 12.4 | AN30: 0.23473014 | AO30: 908.46875
A31: Smartphones | B31: 815 | C31: 0.3292638 | D31: 0.3292638 | E31: 1 | F31: 1630 | G31: 4.1 | H31: 0.3292638 | I31: 815 | J31: #DIV/0! | K31: #DIV/0! | P31: #DIV/0! | Q31: #DIV/0! | R31: 1029.6591 | S31: 0.29036442 | T31: 0.84442048 | U31: 3 | V31: 11326.25 | W31: 11 | X31: 0.29036442 | Y31: 1029.6591 | Z31: 996.63462 | AA31: 0.29525827 | AB31: 1.1736843 | AC31: 4 | AD31: 12956.25 | AE31: 15.1 | AF31: 0.29525827 | AG31: 996.63462 | AH31: 996.63462 | AI31: 0.29525827 | AJ31: 1.1736843 | AK31: 4 | AL31: 12956.25 | AM31: 15.1 | AN31: 0.29525827 | AO31: 996.63462
A32: Tablets | B32: #DIV/0! | C32: #DIV/0! | H32: #DIV/0! | I32: #DIV/0! | J32: 345 | K32: 0.29601449 | L32: 0.29601449 | M32: 1 | N32: 1380 | O32: 4.6 | P32: 0.29601449 | Q32: 345 | R32: 355.5 | S32: 0.35507736 | T32: 0.35507736 | U32: 1 | V32: 711 | W32: 3.4 | X32: 0.35507736 | Y32: 355.5 | Z32: 348.5 | AA32: 0.31609756 | AB32: 0.65109185 | AC32: 2 | AD32: 2091 | AE32: 8 | AF32: 0.31609756 | AG32: 348.5 | AH32: 348.5 | AI32: 0.31609756 | AJ32: 0.65109185 | AK32: 2 | AL32: 2091 | AM32: 8 | AN32: 0.31609756 | AO32: 348.5
A33: Oeste | B33: 937.51739 | C33: 0.29920094 | D33: 2.0382755 | E33: 7 | F33: 21562.9 | G33: 29.9 | H33: 0.29920094 | I33: 937.51739 | J33: 717.31111 | K33: 0.37263236 | L33: 0.74854759 | M33: 2 | N33: 6455.8 | O33: 9.5 | P33: 0.37263236 | Q33: 717.31111 | R33: 864.34455 | S33: 0.31643274 | T33: 5.997707 | U33: 19 | V33: 47538.95 | W33: 67.1 | X33: 0.31643274 | Y33: 864.34455 | Z33: 868.47874 | AA33: 0.31631688 | AB33: 8.7845301 | AC33: 28 | AD33: 75557.65 | AE33: 106.5 | AF33: 0.31631688 | AG33: 868.47874 | AH33: 868.47874 | AI33: 0.31631688 | AJ33: 8.7845301 | AK33: 28 | AL33: 75557.65 | AM33: 106.5 | AN33: 0.31631688 | AO33: 868.47874
A34: Distribuidor | B34: 954.67273 | C34: 0.27652789 | D34: 0.85065502 | E34: 3 | F34: 10501.4 | G34: 12.8 | H34: 0.27652789 | I34: 954.67273 | J34: 520.2 | K34: 0.37889273 | L34: 0.37889273 | M34: 1 | N34: 2080.8 | O34: 4.9 | P34: 0.37889273 | Q34: 520.2 | R34: 927.475 | S34: 0.30429784 | T34: 2.0359352 | U34: 7 | V34: 20404.45 | W34: 24.8 | X34: 0.30429784 | Y34: 927.475 | Z34: 891.53108 | AA34: 0.30016264 | AB34: 3.265483 | AC34: 11 | AD34: 32986.65 | AE34: 42.5 | AF34: 0.30016264 | AG34: 891.53108 | AH34: 891.53108 | AI34: 0.30016264 | AJ34: 3.265483 | AK34: 11 | AL34: 32986.65 | AM34: 42.5 | AN34: 0.30016264 | AO34: 891.53108
A35: Laptops | B35: 954.67273 | C35: 0.27652789 | D35: 0.85065502 | E35: 3 | F35: 10501.4 | G35: 12.8 | H35: 0.27652789 | I35: 954.67273 | J35: #DIV/0! | K35: #DIV/0! | P35: #DIV/0! | Q35: #DIV/0! | R35: 1166.6538 | S35: 0.31766986 | T35: 1.2305162 | U35: 4 | V35: 15166.5 | W35: 14 | X35: 0.31766986 | Y35: 1166.6538 | Z35: 1069.4958 | AA35: 0.30083762 | AB35: 2.0811712 | AC35: 7 | AD35: 25667.9 | AE35: 26.8 | AF35: 0.30083762 | AG35: 1069.4958 | AH35: 1069.4958 | AI35: 0.30083762 | AJ35: 2.0811712 | AK35: 7 | AL35: 25667.9 | AM35: 26.8 | AN35: 0.30083762 | AO35: 1069.4958
A36: Smartphones | B36: #DIV/0! | C36: #DIV/0! | H36: #DIV/0! | I36: #DIV/0! | J36: 520.2 | K36: 0.37889273 | L36: 0.37889273 | M36: 1 | N36: 2080.8 | O36: 4.9 | P36: 0.37889273 | Q36: 520.2 | R36: 548.1 | S36: 0.26447729 | T36: 0.26447729 | U36: 1 | V36: 2192.4 | W36: 3.3 | X36: 0.26447729 | Y36: 548.1 | Z36: 534.15 | AA36: 0.32019096 | AB36: 0.64337002 | AC36: 2 | AD36: 4273.2 | AE36: 8.2 | AF36: 0.32019096 | AG36: 534.15 | AH36: 534.15 | AI36: 0.32019096 | AJ36: 0.64337002 | AK36: 2 | AL36: 4273.2 | AM36: 8.2 | AN36: 0.32019096 | AO36: 534.15
A37: Tablets | B37: #DIV/0! | C37: #DIV/0! | H37: #DIV/0! | I37: #DIV/0! | J37: #DIV/0! | K37: #DIV/0! | P37: #DIV/0! | Q37: #DIV/0! | R37: 609.11 | S37: 0.26637225 | T37: 0.54094177 | U37: 2 | V37: 3045.55 | W37: 7.5 | X37: 0.26637225 | Y37: 609.11 | Z37: 609.11 | AA37: 0.26637225 | AB37: 0.54094177 | AC37: 2 | AD37: 3045.55 | AE37: 7.5 | AF37: 0.26637225 | AG37: 609.11 | AH37: 609.11 | AI37: 0.26637225 | AJ37: 0.54094177 | AK37: 2 | AL37: 3045.55 | AM37: 7.5 | AN37: 0.26637225 | AO37: 609.11
A38: Online | B38: 723.35 | C38: 0.3128845 | D38: 0.3128845 | E38: 1 | F38: 2893.4 | G38: 4.5 | H38: 0.3128845 | I38: 723.35 | J38: 875 | K38: 0.36965486 | L38: 0.36965486 | M38: 1 | N38: 4375 | O38: 4.6 | P38: 0.36965486 | Q38: 875 | R38: 766.31579 | S38: 0.29246909 | T38: 1.4929414 | U38: 5 | V38: 14560 | W38: 17.6 | X38: 0.29246909 | Y38: 766.31579 | Z38: 779.58571 | AA38: 0.31064531 | AB38: 2.1754808 | AC38: 7 | AD38: 21828.4 | AE38: 26.7 | AF38: 0.31064531 | AG38: 779.58571 | AH38: 779.58571 | AI38: 0.31064531 | AJ38: 2.1754808 | AK38: 7 | AL38: 21828.4 | AM38: 26.7 | AN38: 0.31064531 | AO38: 779.58571
A39: Laptops | B39: #DIV/0! | C39: #DIV/0! | H39: #DIV/0! | I39: #DIV/0! | J39: 875 | K39: 0.36965486 | L39: 0.36965486 | M39: 1 | N39: 4375 | O39: 4.6 | P39: 0.36965486 | Q39: 875 | R39: 897.625 | S39: 0.26613703 | T39: 0.53995467 | U39: 2 | V39: 7181 | W39: 6.3 | X39: 0.26613703 | Y39: 897.625 | Z39: 888.92308 | AA39: 0.30532797 | AB39: 0.90960953 | AC39: 3 | AD39: 11556 | AE39: 10.9 | AF39: 0.30532797 | AG39: 888.92308 | AH39: 888.92308 | AI39: 0.30532797 | AJ39: 0.90960953 | AK39: 3 | AL39: 11556 | AM39: 10.9 | AN39: 0.30532797 | AO39: 888.92308
A40: Smartphones | B40: #DIV/0! | C40: #DIV/0! | H40: #DIV/0! | I40: #DIV/0! | J40: #DIV/0! | K40: #DIV/0! | P40: #DIV/0! | Q40: #DIV/0! | R40: 941 | S40: 0.228452 | T40: 0.228452 | U40: 1 | V40: 2823 | W40: 3.7 | X40: 0.228452 | Y40: 941 | Z40: 941 | AA40: 0.228452 | AB40: 0.228452 | AC40: 1 | AD40: 2823 | AE40: 3.7 | AF40: 0.228452 | AG40: 941 | AH40: 941 | AI40: 0.228452 | AJ40: 0.228452 | AK40: 1 | AL40: 2823 | AM40: 3.7 | AN40: 0.228452 | AO40: 941
A41: Tablets | B41: 723.35 | C41: 0.3128845 | D41: 0.3128845 | E41: 1 | F41: 2893.4 | G41: 4.5 | H41: 0.3128845 | I41: 723.35 | J41: #DIV/0! | K41: #DIV/0! | P41: #DIV/0! | Q41: #DIV/0! | R41: 569.5 | S41: 0.37363916 | T41: 0.72453475 | U41: 2 | V41: 4556 | W41: 7.6 | X41: 0.37363916 | Y41: 569.5 | Z41: 620.78333 | AA41: 0.35004161 | AB41: 1.0374192 | AC41: 3 | AD41: 7449.4 | AE41: 12.1 | AF41: 0.35004161 | AG41: 620.78333 | AH41: 620.78333 | AI41: 0.35004161 | AJ41: 1.0374192 | AK41: 3 | AL41: 7449.4 | AM41: 12.1 | AN41: 0.35004161 | AO41: 620.78333
A42: Tienda | B42: 1021.0125 | C42: 0.32350363 | D42: 0.87473596 | E42: 3 | F42: 8168.1 | G42: 12.6 | H42: 0.32350363 | I42: 1021.0125 | J42: #DIV/0! | K42: #DIV/0! | P42: #DIV/0! | Q42: #DIV/0! | R42: 898.17857 | S42: 0.36387133 | T42: 2.4688303 | U42: 7 | V42: 12574.5 | W42: 24.7 | X42: 0.36387133 | Y42: 898.17857 | Z42: 942.84545 | AA42: 0.34797518 | AB42: 3.3435663 | AC42: 10 | AD42: 20742.6 | AE42: 37.3 | AF42: 0.34797518 | AG42: 942.84545 | AH42: 942.84545 | AI42: 0.34797518 | AJ42: 3.3435663 | AK42: 10 | AL42: 20742.6 | AM42: 37.3 | AN42: 0.34797518 | AO42: 942.84545
A43: Laptops | B43: 1180.5333 | C43: 0.33460865 | D43: 0.62373587 | E43: 2 | F43: 7083.2 | G43: 8.5 | H43: 0.33460865 | I43: 1180.5333 | J43: #DIV/0! | K43: #DIV/0! | P43: #DIV/0! | Q43: #DIV/0! | R43: 1117.5667 | S43: 0.36050049 | T43: 1.3900131 | U43: 4 | V43: 6705.4 | W43: 14.1 | X43: 0.36050049 | Y43: 1117.5667 | Z43: 1149.05 | AA43: 0.34719986 | AB43: 2.013749 | AC43: 6 | AD43: 13788.6 | AE43: 22.6 | AF43: 0.34719986 | AG43: 1149.05 | AH43: 1149.05 | AI43: 0.34719986 | AJ43: 2.013749 | AK43: 6 | AL43: 13788.6 | AM43: 22.6 | AN43: 0.34719986 | AO43: 1149.05
A44: Smartphones | B44: #DIV/0! | C44: #DIV/0! | H44: #DIV/0! | I44: #DIV/0! | J44: #DIV/0! | K44: #DIV/0! | P44: #DIV/0! | Q44: #DIV/0! | R44: 689.4 | S44: 0.35809883 | T44: 0.35809883 | U44: 1 | V44: 2068.2 | W44: 3.5 | X44: 0.35809883 | Y44: 689.4 | Z44: 689.4 | AA44: 0.35809883 | AB44: 0.35809883 | AC44: 1 | AD44: 2068.2 | AE44: 3.5 | AF44: 0.35809883 | AG44: 689.4 | AH44: 689.4 | AI44: 0.35809883 | AJ44: 0.35809883 | AK44: 1 | AL44: 2068.2 | AM44: 3.5 | AN44: 0.35809883 | AO44: 689.4
A45: Tablets | B45: 542.45 | C45: 0.25100009 | D45: 0.25100009 | E45: 1 | F45: 1084.9 | G45: 4.1 | H45: 0.25100009 | I45: 542.45 | J45: #DIV/0! | K45: #DIV/0! | P45: #DIV/0! | Q45: #DIV/0! | R45: 760.18 | S45: 0.37295904 | T45: 0.72071838 | U45: 2 | V45: 3800.9 | W45: 7.1 | X45: 0.37295904 | Y45: 760.18 | Z45: 697.97143 | AA45: 0.34587785 | AB45: 0.97171847 | AC45: 3 | AD45: 4885.8 | AE45: 11.2 | AF45: 0.34587785 | AG45: 697.97143 | AH45: 697.97143 | AI45: 0.34587785 | AJ45: 0.97171847 | AK45: 3 | AL45: 4885.8 | AM45: 11.2 | AN45: 0.34587785 | AO45: 697.97143
A46: Sur | B46: 950.65833 | C46: 0.25785727 | D46: 1.3605562 | E46: 5 | F46: 11407.9 | G46: 21.6 | H46: 0.25785727 | I46: 950.65833 | J46: 705.66389 | K46: 0.295209 | L46: 1.8819897 | M46: 7 | N46: 12701.95 | O46: 33.3 | P46: 0.295209 | Q46: 705.66389 | R46: 728.35426 | S46: 0.29800439 | T46: 3.4909169 | U46: 12 | V46: 34232.65 | W46: 42 | X46: 0.29800439 | Y46: 728.35426 | Z46: 757.69481 | AA46: 0.2895457 | AB46: 6.7334629 | AC46: 24 | AD46: 58342.5 | AE46: 96.9 | AF46: 0.2895457 | AG46: 757.69481 | AH46: 757.69481 | AI46: 0.2895457 | AJ46: 6.7334629 | AK46: 24 | AL46: 58342.5 | AM46: 96.9 | AN46: 0.2895457 | AO46: 757.69481
A47: Distribuidor | B47: 695.7 | C47: 0.20209501 | D47: 0.20209501 | E47: 1 | F47: 2782.8 | G47: 4.3 | H47: 0.20209501 | I47: 695.7 | J47: 682.79615 | K47: 0.29464926 | L47: 1.0499638 | M47: 4 | N47: 8876.35 | O47: 19.2 | P47: 0.29464926 | Q47: 682.79615 | R47: 890.8 | S47: 0.37579928 | T47: 0.37579928 | U47: 1 | V47: 4454 | W47: 3.4 | X47: 0.37579928 | Y47: 890.8 | Z47: 732.41591 | AA47: 0.30109631 | AB47: 1.627858 | AC47: 6 | AD47: 16113.15 | AE47: 26.9 | AF47: 0.30109631 | AG47: 732.41591 | AH47: 732.41591 | AI47: 0.30109631 | AJ47: 1.627858 | AK47: 6 | AL47: 16113.15 | AM47: 26.9 | AN47: 0.30109631 | AO47: 732.41591
A48: Laptops | B48: #DIV/0! | C48: #DIV/0! | H48: #DIV/0! | I48: #DIV/0! | J48: 925 | K48: 0.31117375 | L48: 0.56346329 | M48: 2 | N48: 6475 | O48: 9.7 | P48: 0.31117375 | Q48: 925 | R48: #DIV/0! | S48: #DIV/0! | X48: #DIV/0! | Y48: #DIV/0! | Z48: 925 | AA48: 0.31117375 | AB48: 0.56346329 | AC48: 2 | AD48: 6475 | AE48: 9.7 | AF48: 0.31117375 | AG48: 925 | AH48: 925 | AI48: 0.31117375 | AJ48: 0.56346329 | AK48: 2 | AL48: 6475 | AM48: 9.7 | AN48: 0.31117375 | AO48: 925
A49: Smartphones | B49: #DIV/0! | C49: #DIV/0! | H49: #DIV/0! | I49: #DIV/0! | J49: #DIV/0! | K49: #DIV/0! | P49: #DIV/0! | Q49: #DIV/0! | R49: 890.8 | S49: 0.37579928 | T49: 0.37579928 | U49: 1 | V49: 4454 | W49: 3.4 | X49: 0.37579928 | Y49: 890.8 | Z49: 890.8 | AA49: 0.37579928 | AB49: 0.37579928 | AC49: 1 | AD49: 4454 | AE49: 3.4 | AF49: 0.37579928 | AG49: 890.8 | AH49: 890.8 | AI49: 0.37579928 | AJ49: 0.37579928 | AK49: 1 | AL49: 4454 | AM49: 3.4 | AN49: 0.37579928 | AO49: 890.8
A50: Tablets | B50: 695.7 | C50: 0.20209501 | D50: 0.20209501 | E50: 1 | F50: 2782.8 | G50: 4.3 | H50: 0.20209501 | I50: 695.7 | J50: 400.225 | K50: 0.25009266 | L50: 0.48650046 | M50: 2 | N50: 2401.35 | O50: 9.5 | P50: 0.25009266 | Q50: 400.225 | R50: #DIV/0! | S50: #DIV/0! | X50: #DIV/0! | Y50: #DIV/0! | Z50: 518.415 | AA50: 0.224328 | AB50: 0.68859547 | AC50: 3 | AD50: 5184.15 | AE50: 13.8 | AF50: 0.224328 | AG50: 518.415 | AH50: 518.415 | AI50: 0.224328 | AJ50: 0.68859547 | AK50: 3 | AL50: 5184.15 | AM50: 13.8 | AN50: 0.224328 | AO50: 518.415
A51: Online | B51: #DIV/0! | C51: #DIV/0! | H51: #DIV/0! | I51: #DIV/0! | J51: 906.3 | K51: 0.22952665 | L51: 0.22952665 | M51: 1 | N51: 906.3 | O51: 4.7 | P51: 0.22952665 | Q51: 906.3 | R51: 631.82955 | S51: 0.24502221 | T51: 1.5184456 | U51: 6 | V51: 13900.25 | W51: 20.8 | X51: 0.24502221 | Y51: 631.82955 | Z51: 643.76304 | AA51: 0.24407374 | AB51: 1.7479723 | AC51: 7 | AD51: 14806.55 | AE51: 25.5 | AF51: 0.24407374 | AG51: 643.76304 | AH51: 643.76304 | AI51: 0.24407374 | AJ51: 1.7479723 | AK51: 7 | AL51: 14806.55 | AM51: 25.5 | AN51: 0.24407374 | AO51: 643.76304
A52: Laptops | B52: #DIV/0! | C52: #DIV/0! | H52: #DIV/0! | I52: #DIV/0! | J52: #DIV/0! | K52: #DIV/0! | P52: #DIV/0! | Q52: #DIV/0! | R52: 1075.5 | S52: 0.23580262 | T52: 0.47742773 | U52: 2 | V52: 7528.5 | W52: 7.3 | X52: 0.23580262 | Y52: 1075.5 | Z52: 1075.5 | AA52: 0.23580262 | AB52: 0.47742773 | AC52: 2 | AD52: 7528.5 | AE52: 7.3 | AF52: 0.23580262 | AG52: 1075.5 | AH52: 1075.5 | AI52: 0.23580262 | AJ52: 0.47742773 | AK52: 2 | AL52: 7528.5 | AM52: 7.3 | AN52: 0.23580262 | AO52: 1075.5
A53: Smartphones | B53: #DIV/0! | C53: #DIV/0! | H53: #DIV/0! | I53: #DIV/0! | J53: 906.3 | K53: 0.22952665 | L53: 0.22952665 | M53: 1 | N53: 906.3 | O53: 4.7 | P53: 0.22952665 | Q53: 906.3 | R53: #DIV/0! | S53: #DIV/0! | X53: #DIV/0! | Y53: #DIV/0! | Z53: 906.3 | AA53: 0.22952665 | AB53: 0.22952665 | AC53: 1 | AD53: 906.3 | AE53: 4.7 | AF53: 0.22952665 | AG53: 906.3 | AH53: 906.3 | AI53: 0.22952665 | AJ53: 0.22952665 | AK53: 1 | AL53: 906.3 | AM53: 4.7 | AN53: 0.22952665 | AO53: 906.3
A54: Tablets | B54: #DIV/0! | C54: #DIV/0! | H54: #DIV/0! | I54: #DIV/0! | J54: #DIV/0! | K54: #DIV/0! | P54: #DIV/0! | Q54: #DIV/0! | R54: 424.78333 | S54: 0.25591556 | T54: 1.0410179 | U54: 4 | V54: 6371.75 | W54: 13.5 | X54: 0.25591556 | Y54: 424.78333 | Z54: 424.78333 | AA54: 0.25591556 | AB54: 1.0410179 | AC54: 4 | AD54: 6371.75 | AE54: 13.5 | AF54: 0.25591556 | AG54: 424.78333 | AH54: 424.78333 | AI54: 0.25591556 | AJ54: 1.0410179 | AK54: 4 | AL54: 6371.75 | AM54: 13.5 | AN54: 0.25591556 | AO54: 424.78333
A55: Tienda | B55: 1078.1375 | C55: 0.2758484 | D55: 1.1584612 | E55: 4 | F55: 8625.1 | G55: 17.3 | H55: 0.2758484 | I55: 1078.1375 | J55: 729.825 | K55: 0.31730209 | L55: 0.60249933 | M55: 2 | N55: 2919.3 | O55: 9.4 | P55: 0.31730209 | Q55: 729.825 | R55: 793.92 | S55: 0.32256399 | T55: 1.596672 | U55: 5 | V55: 15878.4 | W55: 17.8 | X55: 0.32256399 | Y55: 793.92 | Z55: 856.9625 | AA55: 0.3073107 | AB55: 3.3576326 | AC55: 11 | AD55: 27422.8 | AE55: 44.5 | AF55: 0.3073107 | AG55: 856.9625 | AH55: 856.9625 | AI55: 0.3073107 | AJ55: 3.3576326 | AK55: 11 | AL55: 27422.8 | AM55: 44.5 | AN55: 0.3073107 | AO55: 856.9625
A56: Laptops | B56: 1082.05 | C56: 0.27904441 | D56: 0.59345746 | E56: 2 | F56: 4328.2 | G56: 8.9 | H56: 0.27904441 | I56: 1082.05 | J56: 740.35 | K56: 0.33202314 | L56: 0.33202314 | M56: 1 | N56: 2221.05 | O56: 4.6 | P56: 0.33202314 | Q56: 740.35 | R56: 902 | S56: 0.29480876 | T56: 0.29480876 | U56: 1 | V56: 3608 | W56: 3.9 | X56: 0.29480876 | Y56: 902 | Z56: 923.38636 | AA56: 0.2962288 | AB56: 1.2202894 | AC56: 4 | AD56: 10157.25 | AE56: 17.4 | AF56: 0.2962288 | AG56: 923.38636 | AH56: 923.38636 | AI56: 0.2962288 | AJ56: 1.2202894 | AK56: 4 | AL56: 10157.25 | AM56: 17.4 | AN56: 0.2962288 | AO56: 923.38636
A57: Smartphones | B57: 1074.225 | C57: 0.2726291 | D57: 0.56500376 | E57: 2 | F57: 4296.9 | G57: 8.4 | H57: 0.2726291 | I57: 1074.225 | J57: #DIV/0! | K57: #DIV/0! | P57: #DIV/0! | Q57: #DIV/0! | R57: 939.17778 | S57: 0.34552682 | T57: 0.69549354 | U57: 2 | V57: 8452.6 | W57: 7.1 | X57: 0.34552682 | Y57: 939.17778 | Z57: 980.73077 | AA57: 0.32095847 | AB57: 1.2604973 | AC57: 4 | AD57: 12749.5 | AE57: 15.5 | AF57: 0.32095847 | AG57: 980.73077 | AH57: 980.73077 | AI57: 0.32095847 | AJ57: 1.2604973 | AK57: 4 | AL57: 12749.5 | AM57: 15.5 | AN57: 0.32095847 | AO57: 980.73077
A58: Tablets | B58: #DIV/0! | C58: #DIV/0! | H58: #DIV/0! | I58: #DIV/0! | J58: 698.25 | K58: 0.27047619 | L58: 0.27047619 | M58: 1 | N58: 698.25 | O58: 4.8 | P58: 0.27047619 | Q58: 698.25 | R58: 545.4 | S58: 0.29795432 | T58: 0.60636973 | U58: 2 | V58: 3817.8 | W58: 6.8 | X58: 0.29795432 | Y58: 545.4 | Z58: 564.50625 | AA58: 0.29370578 | AB58: 0.87684592 | AC58: 3 | AD58: 4516.05 | AE58: 11.6 | AF58: 0.29370578 | AG58: 564.50625 | AH58: 564.50625 | AI58: 0.29370578 | AJ58: 0.87684592 | AK58: 3 | AL58: 4516.05 | AM58: 11.6 | AN58: 0.29370578 | AO58: 564.50625
A59: Total general | B59: 966.3475 | C59: 0.29002766 | D59: 6.367824 | E59: 22 | F59: 57980.85 | G59: 94.2 | H59: 0.29002766 | I59: 966.3475 | J59: 721.12258 | K59: 0.3028958 | L59: 6.3553273 | M59: 22 | N59: 44709.6 | O59: 105.2 | P59: 0.3028958 | Q59: 721.12258 | R59: 830.6481 | S59: 0.30774026 | T59: 17.209719 | U59: 56 | V59: 152839.25 | W59: 199.7 | X59: 0.30774026 | Y59: 830.6481 | Z59: 835.06438 | AA59: 0.30287356 | AB59: 29.932871 | AC59: 100 | AD59: 255529.7 | AE59: 399.1 | AF59: 0.30287356 | AG59: 835.06438 | AH59: 835.06438 | AI59: 0.30287356 | AJ59: 29.932871 | AK59: 100 | AL59: 255529.7 | AM59: 399.1 | AN59: 0.30287356 | AO59: 835.06438

Sheet Datos_Ventas_Completos
A1: ID_Transaccion | B1: Fecha | C1: Region | D1: Canal_Venta | E1: Categoria | F1: Producto | G1: Vendedor | H1: Precio_Unitario | I1: Cantidad | J1: Ingresos_Totales | K1: Costo_Unitario | L1: Margen_Bruto | M1: Satisfaccion_Cliente | N1: Tiempo_Entrega | O1: Descuento_Aplicado | P1: Metodo_Pago | Q1: Rentabilidad_Pct | R1: Categoria_Cliente | S1: Trimestre | T1: Semana_Año | U1: Eficiencia_Entrega | V1: Antigüedad_Vendedor | W1: Satisfaccion_Laboral_Vendedor | X1: Stock_Disponible | Y1: Z_Score_Ingresos | Z1: Outlier_Z | AA1: Outlier_IQR | AB1: Media | AC1: =AVERAGE(J2:J101) -> 2555.297 | AG1: Q1_Ingresos | AH1: =_xlfn.QUARTILE.INC(J2:J101,1) -> 1379 | AJ1: Desviacion estándar
A2: TXN001 | B2: 45373 | C2: Norte | D2: Online | E2: Tablets | F2: Galaxy Tab S9 | G2: José Martín | H2: 528 | I2: 2 | J2: 1056 | K2: 388.26 | L2: 279.48 | M2: 4.8 | N2: 1 | O2: 0 | P2: Transferencia | Q2: =L2/J2 -> 0.26465909 | R2: =IF(M2>4.5,"Premium",IF(M2>4,"Estandar","Riesgo")) -> Premium | S2: ="Q"&ROUNDUP(MONTH(B2)/3,0) -> Q1 | T2: =WEEKDAY(B2) -> 6 | U2: =IF(N2<=2,"Excelente",IF(N2<=4,"Buena","Mejorable")) -> Excelente | V2: =VLOOKUP(G2,Datos_Empleados!B:E,4,FALSE) -> 12 | W2: =VLOOKUP(G2,Datos_Empleados!B:I,8,FALSE) -> 4.5 | X2: =INDEX(Datos_Productos!G:G,MATCH(F2,Datos_Productos!B:B,0)) -> 44 | Y2: =(J2-AVERAGE($J$2:$J$101))/_xlfn.STDEV.S($J$2:$J$101) -> -1.0613243 | Z2: =IF(ABS(Y2)>2.5,"Sí","No") -> No | AA2: =IF(OR(J2<$AH$4,J2>$AH$5),"Sí","No") -> No | AB2: Desv | AC2: =_xlfn.STDEV.S(J2:J101) -> 1412.6662 | AG2: Q3_Ingresos | AH2: =_xlfn.QUARTILE.INC(J2:J101,3) -> 3434.25 | AJ2: Con Outliers | AK2: =_xlfn.STDEV.P(J2:J101) -> 1405.5851
A3: TXN002 | B3: 45346 | C3: Norte | D3: Online | E3: Laptops | F3: Gaming Pro X1 | G3: José Martín | H3: 1317 | I3: 5 | J3: 6585 | K3: 938.03 | L3: 1894.84 | M3: 4.4 | N3: 6 | O3: 0 | P3: Transferencia | Q3: =L3/J3 -> 0.28775095 | R3: =IF(M3>4.5,"Premium",IF(M3>4,"Estandar","Riesgo")) -> Estandar | S3: ="Q"&ROUNDUP(MONTH(B3)/3,0) -> Q1 | T3: =WEEKDAY(B3) -> 7 | U3: =IF(N3<=2,"Excelente",IF(N3<=4,"Buena","Mejorable")) -> Mejorable | V3: =VLOOKUP(G3,Datos_Empleados!B:E,4,FALSE) -> 12 | W3: =VLOOKUP(G3,Datos_Empleados!B:I,8,FALSE) -> 4.5 | X3: =INDEX(Datos_Productos!G:G,MATCH(F3,Datos_Productos!B:B,0)) -> 41 | Y3: =(J3-AVERAGE($J$2:$J$101))/_xlfn.STDEV.S($J$2:$J$101) -> 2.8525514 | Z3: =IF(ABS(Y3)>2.5,"Sí","No") -> Sí | AA3: =IF(OR(J3<$AH$4,J3>$AH$5),"Sí","No") -> Sí | AB3: n | AC3: =COUNT(J2:J101) -> 100 | AG3: IQR_Ingresos | AH3: =AH2-AH1 -> 2055.25 | AJ3: Sin Outliers | AK3: {=_xlfn.STDEV.P(IF(AA2:AA101="No",J2:J101))} -> 1352.7541
A4: TXN003 | B4: 45345 | C4: Sur | D4: Tienda | E4: Tablets | F4: Galaxy Tab S9 | G4: Ana García | H4: 463 | I4: 4 | J4: 1666.8 | K4: 303.53 | L4: 574.09 | M4: 3.4 | N4: 7 | O4: 0.1 | P4: Efectivo | Q4: =L4/J4 -> 0.34442645 | R4: =IF(M4>4.5,"Premium",IF(M4>4,"Estandar","Riesgo")) -> Riesgo | S4: ="Q"&ROUNDUP(MONTH(B4)/3,0) -> Q1 | T4: =WEEKDAY(B4) -> 6 | U4: =IF(N4<=2,"Excelente",IF(N4<=4,"Buena","Mejorable")) -> Mejorable | V4: =VLOOKUP(G4,Datos_Empleados!B:E,4,FALSE) -> 37 | W4: =VLOOKUP(G4,Datos_Empleados!B:I,8,FALSE) -> 3.6 | X4: =INDEX(Datos_Productos!G:G,MATCH(F4,Datos_Productos!B:B,0)) -> 44 | Y4: =(J4-AVERAGE($J$2:$J$101))/_xlfn.STDEV.S($J$2:$J$101) -> -0.62895041 | Z4: =IF(ABS(Y4)>2.5,"Sí","No") -> No | AA4: =IF(OR(J4<$AH$4,J4>$AH$5),"Sí","No") -> No | AB4: t | AC4: =TINV(0.05,AC3-1) -> 1.984217 | AG4: Limite_Inferior | AH4: =AH1-1.5*AH3 -> -1703.875
A5: TXN004 | B5: 45305 | C5: Norte | D5: Tienda | E5: Laptops | F5: Business Y2 | G5: Pedro González | H5: 1070 | I5: 1 | J5: 909.5 | K5: 756.75 | L5: 266.26 | M5: 4.9 | N5: 4 | O5: 0.15 | P5: Tarjeta | Q5: =L5/J5 -> 0.29275426 | R5: =IF(M5>4.5,"Premium",IF(M5>4,"Estandar","Riesgo")) -> Premium | S5: ="Q"&ROUNDUP(MONTH(B5)/3,0) -> Q1 | T5: =WEEKDAY(B5) -> 1 | U5: =IF(N5<=2,"Excelente",IF(N5<=4,"Buena","Mejorable")) -> Buena | V5: =VLOOKUP(G5,Datos_Empleados!B:E,4,FALSE) -> 32 | W5: =VLOOKUP(G5,Datos_Empleados!B:I,8,FALSE) -> 4 | X5: =INDEX(Datos_Productos!G:G,MATCH(F5,Datos_Productos!B:B,0)) -> 41 | Y5: =(J5-AVERAGE($J$2:$J$101))/_xlfn.STDEV.S($J$2:$J$101) -> -1.1650289 | Z5: =IF(ABS(Y5)>2.5,"Sí","No") -> No | AA5: =IF(OR(J5<$AH$4,J5>$AH$5),"Sí","No") -> No | AB5: Error | AC5: =AC2/SQRT(AC3) -> 141.26662 | AG5: Limite_Superior | AH5: =AH2+1.5*AH3 -> 6517.125
A6: TXN005 | B6: 45362 | C6: Este | D6: Distribuidor | E6: Tablets | F6: Galaxy Tab S9 | G6: José Martín | H6: 371 | I6: 1 | J6: 352.45 | K6: 279.96 | L6: 86.49 | M6: 5 | N6: 7 | O6: 0.05 | P6: Tarjeta | Q6: =L6/J6 -> 0.24539651 | R6: =IF(M6>4.5,"Premium",IF(M6>4,"Estandar","Riesgo")) -> Premium | S6: ="Q"&ROUNDUP(MONTH(B6)/3,0) -> Q1 | T6: =WEEKDAY(B6) -> 2 | U6: =IF(N6<=2,"Excelente",IF(N6<=4,"Buena","Mejorable")) -> Mejorable | V6: =VLOOKUP(G6,Datos_Empleados!B:E,4,FALSE) -> 12 | W6: =VLOOKUP(G6,Datos_Empleados!B:I,8,FALSE) -> 4.5 | X6: =INDEX(Datos_Productos!G:G,MATCH(F6,Datos_Productos!B:B,0)) -> 44 | Y6: =(J6-AVERAGE($J$2:$J$101))/_xlfn.STDEV.S($J$2:$J$101) -> -1.5593542 | Z6: =IF(ABS(Y6)>2.5,"Sí","No") -> No | AA6: =IF(OR(J6<$AH$4,J6>$AH$5),"Sí","No") -> No | AB6: LI | AC6: =AC1-(AC4*AC5) -> 2274.9934 | AG6: Media | AH6: =AVERAGE(J:J) -> 2555.297
A7: TXN006 | B7: 45304 | C7: Oeste | D7: Tienda | E7: Smartphones | F7: Pixel 8 Pro | G7: Pedro González | H7: 766 | I7: 3 | J7: 2068.2 | K7: 491.7 | L7: 740.62 | M7: 3.5 | N7: 6 | O7: 0.1 | P7: Transferencia | Q7: =L7/J7 -> 0.35809883 | R7: =IF(M7>4.5,"Premium",IF(M7>4,"Estandar","Riesgo")) -> Riesgo | S7: ="Q"&ROUNDUP(MONTH(B7)/3,0) -> Q1 | T7: =WEEKDAY(B7) -> 7 | U7: =IF(N7<=2,"Excelente",IF(N7<=4,"Buena","Mejorable")) -> Mejorable | V7: =VLOOKUP(G7,Datos_Empleados!B:E,4,FALSE) -> 32 | W7: =VLOOKUP(G7,Datos_Empleados!B:I,8,FALSE) -> 4 | X7: =INDEX(Datos_Productos!G:G,MATCH(F7,Datos_Productos!B:B,0)) -> 37 | Y7: =(J7-AVERAGE($J$2:$J$101))/_xlfn.STDEV.S($J$2:$J$101) -> -0.34480686 | Z7: =IF(ABS(Y7)>2.5,"Sí","No") -> No | AA7: =IF(OR(J7<$AH$4,J7>$AH$5),"Sí","No") -> No | AB7: LS | AC7: =AC1+(AC4*AC5) -> 2835.6006 | AG7: Outlier_IQR | AH7: =AVERAGEIF(AA2:AA101,"No",J2:J101) -> 2514.5929
A8: TXN007 | B8: 45301 | C8: Sur | D8: Distribuidor | E8: Tablets | F8: iPad Air | G8: María Rodríguez | H8: 773 | I8: 4 | J8: 2782.8 | K8: 616.78 | L8: 562.39 | M8: 4.3 | N8: 5 | O8: 0.1 | P8: Tarjeta | Q8: =L8/J8 -> 0.20209501 | R8: =IF(M8>4.5,"Premium",IF(M8>4,"Estandar","Riesgo")) -> Estandar | S8: ="Q"&ROUNDUP(MONTH(B8)/3,0) -> Q1 | T8: =WEEKDAY(B8) -> 4 | U8: =IF(N8<=2,"Excelente",IF(N8<=4,"Buena","Mejorable")) -> Mejorable | V8: =VLOOKUP(G8,Datos_Empleados!B:E,4,FALSE) -> 30 | W8: =VLOOKUP(G8,Datos_Empleados!B:I,8,FALSE) -> 4.2 | X8: =INDEX(Datos_Productos!G:G,MATCH(F8,Datos_Productos!B:B,0)) -> 38 | Y8: =(J8-AVERAGE($J$2:$J$101))/_xlfn.STDEV.S($J$2:$J$101) -> 0.16104512 | Z8: =IF(ABS(Y8)>2.5,"Sí","No") -> No | AA8: =IF(OR(J8<$AH$4,J8>$AH$5),"Sí","No") -> No
A9: TXN008 | B9: 45379 | C9: Este | D9: Online | E9: Laptops | F9: Gaming Pro X1 | G9: Pedro González | H9: 1210 | I9: 3 | J9: 3630 | K9: 777.06 | L9: 1298.83 | M9: 4.9 | N9: 6 | O9: 0 | P9: Efectivo | Q9: =L9/J9 -> 0.35780441 | R9: =IF(M9>4.5,"Premium",IF(M9>4,"Estandar","Riesgo")) -> Premium | S9: ="Q"&ROUNDUP(MONTH(B9)/3,0) -> Q1 | T9: =WEEKDAY(B9) -> 5 | U9: =IF(N9<=2,"Excelente",IF(N9<=4,"Buena","Mejorable")) -> Mejorable | V9: =VLOOKUP(G9,Datos_Empleados!B:E,4,FALSE) -> 32 | W9: =VLOOKUP(G9,Datos_Empleados!B:I,8,FALSE) -> 4 | X9: =INDEX(Datos_Productos!G:G,MATCH(F9,Datos_Productos!B:B,0)) -> 41 | Y9: =(J9-AVERAGE($J$2:$J$101))/_xlfn.STDEV.S($J$2:$J$101) -> 0.76076216 | Z9: =IF(ABS(Y9)>2.5,"Sí","No") -> No | AA9: =IF(OR(J9<$AH$4,J9>$AH$5),"Sí","No") -> No | AB9: Estamos 95% seguros de que el ingreso promedio verdadero se encuentra entre [LI] y [LS]. | AG9: Correlaciones
A10: TXN009 | B10: 45319 | C10: Oeste | D10: Tienda | E10: Tablets | F10: Galaxy Tab S9 | G10: María Rodríguez | H10: 571 | I10: 2 | J10: 1084.9 | K10: 427.68 | L10: 272.31 | M10: 4.1 | N10: 6 | O10: 0.05 | P10: Transferencia | Q10: =L10/J10 -> 0.25100009 | R10: =IF(M10>4.5,"Premium",IF(M10>4,"Estandar","Riesgo")) -> Estandar | S10: ="Q"&ROUNDUP(MONTH(B10)/3,0) -> Q1 | T10: =WEEKDAY(B10) -> 1 | U10: =IF(N10<=2,"Excelente",IF(N10<=4,"Buena","Mejorable")) -> Mejorable | V10: =VLOOKUP(G10,Datos_Empleados!B:E,4,FALSE) -> 30 | W10: =VLOOKUP(G10,Datos_Empleados!B:I,8,FALSE) -> 4.2 | X10: =INDEX(Datos_Productos!G:G,MATCH(F10,Datos_Productos!B:B,0)) -> 44 | Y10: =(J10-AVERAGE($J$2:$J$101))/_xlfn.STDEV.S($J$2:$J$101) -> -1.0408665 | Z10: =IF(ABS(Y10)>2.5,"Sí","No") -> No | AA10: =IF(OR(J10<$AH$4,J10>$AH$5),"Sí","No") -> No | AG10: Ingresos vs Cantidad
A11: TXN010 | B11: 45346 | C11: Oeste | D11: Tienda | E11: Laptops | F11: Gaming Pro X1 | G11: Miguel Torres | H11: 893 | I11: 1 | J11: 893 | K11: 563.1 | L11: 329.9 | M11: 3.3 | N11: 6 | O11: 0 | P11: Efectivo | Q11: =L11/J11 -> 0.36942889 | R11: =IF(M11>4.5,"Premium",IF(M11>4,"Estandar","Riesgo")) -> Riesgo | S11: ="Q"&ROUNDUP(MONTH(B11)/3,0) -> Q1 | T11: =WEEKDAY(B11) -> 7 | U11: =IF(N11<=2,"Excelente",IF(N11<=4,"Buena","Mejorable")) -> Mejorable | V11: =VLOOKUP(G11,Datos_Empleados!B:E,4,FALSE) -> 12 | W11: =VLOOKUP(G11,Datos_Empleados!B:I,8,FALSE) -> 4.3 | X11: =INDEX(Datos_Productos!G:G,MATCH(F11,Datos_Productos!B:B,0)) -> 41 | Y11: =(J11-AVERAGE($J$2:$J$101))/_xlfn.STDEV.S($J$2:$J$101) -> -1.176709 | Z11: =IF(ABS(Y11)>2.5,"Sí","No") -> No | AA11: =IF(OR(J11<$AH$4,J11>$AH$5),"Sí","No") -> No | AG11: Con Outliers | AH11: =CORREL(J2:J101,I2:I101) -> 0.75392663
A12: TXN011 | B12: 45368 | C12: Norte | D12: Tienda | E12: Smartphones | F12: Pixel 8 Pro | G12: Miguel Torres | H12: 1141 | I12: 3 | J12: 3423 | K12: 839.84 | L12: 903.48 | M12: 3.2 | N12: 5 | O12: 0 | P12: Efectivo | Q12: =L12/J12 -> 0.26394391 | R12: =IF(M12>4.5,"Premium",IF(M12>4,"Estandar","Riesgo")) -> Riesgo | S12: ="Q"&ROUNDUP(MONTH(B12)/3,0) -> Q1 | T12: =WEEKDAY(B12) -> 1 | U12: =IF(N12<=2,"Excelente",IF(N12<=4,"Buena","Mejorable")) -> Mejorable | V12: =VLOOKUP(G12,Datos_Empleados!B:E,4,FALSE) -> 12 | W12: =VLOOKUP(G12,Datos_Empleados!B:I,8,FALSE) -> 4.3 | X12: =INDEX(Datos_Productos!G:G,MATCH(F12,Datos_Productos!B:B,0)) -> 37 | Y12: =(J12-AVERAGE($J$2:$J$101))/_xlfn.STDEV.S($J$2:$J$101) -> 0.61423073 | Z12: =IF(ABS(Y12)>2.5,"Sí","No") -> No | AA12: =IF(OR(J12<$AH$4,J12>$AH$5),"Sí","No") -> No | AG12: Sin Outliers | AH12: {=CORREL(IF(AA2:AA101="No",J2:J101),IF(AA2:AA101="No",I2:I101))} -> 0.75022032
A13: TXN012 | B13: 45374 | C13: Este | D13: Online | E13: Smartphones | F13: Galaxy S24 | G13: María Rodríguez | H13: 1064 | I13: 1 | J13: 957.6 | K13: 845.22 | L13: 196.9 | M13: 4.5 | N13: 5 | O13: 0.1 | P13: Tarjeta | Q13: =L13/J13 -> 0.20561821 | R13: =IF(M13>4.5,"Premium",IF(M13>4,"Estandar","Riesgo")) -> Estandar | S13: ="Q"&ROUNDUP(MONTH(B13)/3,0) -> Q1 | T13: =WEEKDAY(B13) -> 7 | U13: =IF(N13<=2,"Excelente",IF(N13<=4,"Buena","Mejorable")) -> Mejorable | V13: =VLOOKUP(G13,Datos_Empleados!B:E,4,FALSE) -> 30 | W13: =VLOOKUP(G13,Datos_Empleados!B:I,8,FALSE) -> 4.2 | X13: =INDEX(Datos_Productos!G:G,MATCH(F13,Datos_Productos!B:B,0)) -> 35 | Y13: =(J13-AVERAGE($J$2:$J$101))/_xlfn.STDEV.S($J$2:$J$101) -> -1.1309798 | Z13: =IF(ABS(Y13)>2.5,"Sí","No") -> No | AA13: =IF(OR(J13<$AH$4,J13>$AH$5),"Sí","No") -> No | AG13: La eliminación de outliers reduce la variabilidad de los datos y puede modificar ligeramente la media y las correlaciones, permitiendo un análisis más representativo del comportamiento general.
A14: TXN013 | B14: 45372 | C14: Este | D14: Distribuidor | E14: Tablets | F14: Surface Pro 9 | G14: José Martín | H14: 456 | I14: 3 | J14: 1299.6 | K14: 322.79 | L14: 379.64 | M14: 4.6 | N14: 5 | O14: 0.05 | P14: Tarjeta | Q14: =L14/J14 -> 0.29212065 | R14: =IF(M14>4.5,"Premium",IF(M14>4,"Estandar","Riesgo")) -> Premium | S14: ="Q"&ROUNDUP(MONTH(B14)/3,0) -> Q1 | T14: =WEEKDAY(B14) -> 5 | U14: =IF(N14<=2,"Excelente",IF(N14<=4,"Buena","Mejorable")) -> Mejorable | V14: =VLOOKUP(G14,Datos_Empleados!B:E,4,FALSE) -> 12 | W14: =VLOOKUP(G14,Datos_Empleados!B:I,8,FALSE) -> 4.5 | X14: =INDEX(Datos_Productos!G:G,MATCH(F14,Datos_Productos!B:B,0)) -> 37 | Y14: =(J14-AVERAGE($J$2:$J$101))/_xlfn.STDEV.S($J$2:$J$101) -> -0.88888443 | Z14: =IF(ABS(Y14)>2.5,"Sí","No") -> No | AA14: =IF(OR(J14<$AH$4,J14>$AH$5),"Sí","No") -> No
A15: TXN014 | B15: 45368 | C15: Este | D15: Tienda | E15: Laptops | F15: Gaming Pro X1 | G15: Pedro González | H15: 1114 | I15: 2 | J15: 2228 | K15: 722.07 | L15: 783.87 | M15: 4.1 | N15: 1 | O15: 0 | P15: Tarjeta | Q15: =L15/J15 -> 0.35182675 | R15: =IF(M15>4.5,"Premium",IF(M15>4,"Estandar","Riesgo")) -> Estandar | S15: ="Q"&ROUNDUP(MONTH(B15)/3,0) -> Q1 | T15: =WEEKDAY(B15) -> 1 | U15: =IF(N15<=2,"Excelente",IF(N15<=4,"Buena","Mejorable")) -> Excelente | V15: =VLOOKUP(G15,Datos_Empleados!B:E,4,FALSE) -> 32 | W15: =VLOOKUP(G15,Datos_Empleados!B:I,8,FALSE) -> 4 | X15: =INDEX(Datos_Productos!G:G,MATCH(F15,Datos_Productos!B:B,0)) -> 41 | Y15: =(J15-AVERAGE($J$2:$J$101))/_xlfn.STDEV.S($J$2:$J$101) -> -0.23168743 | Z15: =IF(ABS(Y15)>2.5,"Sí","No") -> No | AA15: =IF(OR(J15<$AH$4,J15>$AH$5),"Sí","No") -> No | AG15: Precio | AH15: Valor variable
A16: TXN015 | B16: 45354 | C16: Norte | D16: Distribuidor | E16: Laptops | F16: Gaming Pro X1 | G16: Miguel Torres | H16: 1362 | I16: 2 | J16: 2451.6 | K16: 960.94 | L16: 721.91 | M16: 4.2 | N16: 2 | O16: 0.1 | P16: Transferencia | Q16: =L16/J16 -> 0.29446484 | R16: =IF(M16>4.5,"Premium",IF(M16>4,"Estandar","Riesgo")) -> Estandar | S16: ="Q"&ROUNDUP(MONTH(B16)/3,0) -> Q1 | T16: =WEEKDAY(B16) -> 1 | U16: =IF(N16<=2,"Excelente",IF(N16<=4,"Buena","Mejorable")) -> Excelente | V16: =VLOOKUP(G16,Datos_Empleados!B:E,4,FALSE) -> 12 | W16: =VLOOKUP(G16,Datos_Empleados!B:I,8,FALSE) -> 4.3 | X16: =INDEX(Datos_Productos!G:G,MATCH(F16,Datos_Productos!B:B,0)) -> 41 | Y16: =(J16-AVERAGE($J$2:$J$101))/_xlfn.STDEV.S($J$2:$J$101) -> -0.073405167 | Z16: =IF(ABS(Y16)>2.5,"Sí","No") -> No | AA16: =IF(OR(J16<$AH$4,J16>$AH$5),"Sí","No") -> No | AG16: Cantidad | AH16: fórmula
A17: TXN016 | B17: 45380 | C17: Sur | D17: Distribuidor | E17: Smartphones | F17: Galaxy S24 | G17: Pedro González | H17: 1048 | I17: 5 | J17: 4454 | K17: 654.16 | L17: 1673.81 | M17: 3.4 | N17: 3 | O17: 0.15 | P17: Tarjeta | Q17: =L17/J17 -> 0.37579928 | R17: =IF(M17>4.5,"Premium",IF(M17>4,"Estandar","Riesgo")) -> Riesgo | S17: ="Q"&ROUNDUP(MONTH(B17)/3,0) -> Q1 | T17: =WEEKDAY(B17) -> 6 | U17: =IF(N17<=2,"Excelente",IF(N17<=4,"Buena","Mejorable")) -> Buena | V17: =VLOOKUP(G17,Datos_Empleados!B:E,4,FALSE) -> 32 | W17: =VLOOKUP(G17,Datos_Empleados!B:I,8,FALSE) -> 4 | X17: =INDEX(Datos_Productos!G:G,MATCH(F17,Datos_Productos!B:B,0)) -> 35 | Y17: =(J17-AVERAGE($J$2:$J$101))/_xlfn.STDEV.S($J$2:$J$101) -> 1.3440563 | Z17: =IF(ABS(Y17)>2.5,"Sí","No") -> No | AA17: =IF(OR(J17<$AH$4,J17>$AH$5),"Sí","No") -> No | AG17: Ingresos | AH17: =H2*Satisfaccion_Cliente -> 1056
A18: TXN017 | B18: 45367 | C18: Sur | D18: Distribuidor | E18: Laptops | F18: Gaming Pro X1 | G18: Carlos López | H18: 860 | I18: 2 | J18: 1720 | K18: 671.73 | L18: 376.54 | M18: 4.7 | N18: 1 | O18: 0 | P18: Transferencia | Q18: =L18/J18 -> 0.2189186 | R18: =IF(M18>4.5,"Premium",IF(M18>4,"Estandar","Riesgo")) -> Premium | S18: ="Q"&ROUNDUP(MONTH(B18)/3,0) -> Q1 | T18: =WEEKDAY(B18) -> 7 | U18: =IF(N18<=2,"Excelente",IF(N18<=4,"Buena","Mejorable")) -> Excelente | V18: =VLOOKUP(G18,Datos_Empleados!B:E,4,FALSE) -> 10 | W18: =VLOOKUP(G18,Datos_Empleados!B:I,8,FALSE) -> 4.4 | X18: =INDEX(Datos_Productos!G:G,MATCH(F18,Datos_Productos!B:B,0)) -> 41 | Y18: =(J18-AVERAGE($J$2:$J$101))/_xlfn.STDEV.S($J$2:$J$101) -> -0.59129113 | Z18: =IF(ABS(Y18)>2.5,"Sí","No") -> No | AA18: =IF(OR(J18<$AH$4,J18>$AH$5),"Sí","No") -> No
A19: TXN018 | B19: 45322 | C19: Este | D19: Distribuidor | E19: Smartphones | F19: iPhone 15 Pro | G19: María Rodríguez | H19: 1184 | I19: 5 | J19: 5032 | K19: 767.94 | L19: 1768.25 | M19: 3.9 | N19: 4 | O19: 0.15 | P19: Tarjeta | Q19: =L19/J19 -> 0.35140103 | R19: =IF(M19>4.5,"Premium",IF(M19>4,"Estandar","Riesgo")) -> Riesgo | S19: ="Q"&ROUNDUP(MONTH(B19)/3,0) -> Q1 | T19: =WEEKDAY(B19) -> 4 | U19: =IF(N19<=2,"Excelente",IF(N19<=4,"Buena","Mejorable")) -> Buena | V19: =VLOOKUP(G19,Datos_Empleados!B:E,4,FALSE) -> 30 | W19: =VLOOKUP(G19,Datos_Empleados!B:I,8,FALSE) -> 4.2 | X19: =INDEX(Datos_Productos!G:G,MATCH(F19,Datos_Productos!B:B,0)) -> 38 | Y19: =(J19-AVERAGE($J$2:$J$101))/_xlfn.STDEV.S($J$2:$J$101) -> 1.7532117 | Z19: =IF(ABS(Y19)>2.5,"Sí","No") -> No | AA19: =IF(OR(J19<$AH$4,J19>$AH$5),"Sí","No") -> No
A20: TXN019 | B20: 45304 | C20: Norte | D20: Distribuidor | E20: Smartphones | F20: Galaxy S24 | G20: Carmen Ruiz | H20: 1020 | I20: 4 | J20: 4080 | K20: 749.37 | L20: 1082.53 | M20: 5 | N20: 1 | O20: 0 | P20: Tarjeta | Q20: =L20/J20 -> 0.26532598 | R20: =IF(M20>4.5,"Premium",IF(M20>4,"Estandar","Riesgo")) -> Premium | S20: ="Q"&ROUNDUP(MONTH(B20)/3,0) -> Q1 | T20: =WEEKDAY(B20) -> 7 | U20: =IF(N20<=2,"Excelente",IF(N20<=4,"Buena","Mejorable")) -> Excelente | V20: =VLOOKUP(G20,Datos_Empleados!B:E,4,FALSE) -> 15 | W20: =VLOOKUP(G20,Datos_Empleados!B:I,8,FALSE) -> 4.7 | X20: =INDEX(Datos_Productos!G:G,MATCH(F20,Datos_Productos!B:B,0)) -> 35 | Y20: =(J20-AVERAGE($J$2:$J$101))/_xlfn.STDEV.S($J$2:$J$101) -> 1.0793087 | Z20: =IF(ABS(Y20)>2.5,"Sí","No") -> No | AA20: =IF(OR(J20<$AH$4,J20>$AH$5),"Sí","No") -> No
A21: TXN020 | B21: 45343 | C21: Este | D21: Online | E21: Laptops | F21: Gaming Pro X1 | G21: José Martín | H21: 1349 | I21: 4 | J21: 5126.2 | K21: 923.22 | L21: 1617.95 | M21: 3.6 | N21: 2 | O21: 0.05 | P21: Tarjeta | Q21: =L21/J21 -> 0.31562366 | R21: =IF(M21>4.5,"Premium",IF(M21>4,"Estandar","Riesgo")) -> Riesgo | S21: ="Q"&ROUNDUP(MONTH(B21)/3,0) -> Q1 | T21: =WEEKDAY(B21) -> 4 | U21: =IF(N21<=2,"Excelente",IF(N21<=4,"Buena","Mejorable")) -> Excelente | V21: =VLOOKUP(G21,Datos_Empleados!B:E,4,FALSE) -> 12 | W21: =VLOOKUP(G21,Datos_Empleados!B:I,8,FALSE) -> 4.5 | X21: =INDEX(Datos_Productos!G:G,MATCH(F21,Datos_Productos!B:B,0)) -> 41 | Y21: =(J21-AVERAGE($J$2:$J$101))/_xlfn.STDEV.S($J$2:$J$101) -> 1.8198942 | Z21: =IF(ABS(Y21)>2.5,"Sí","No") -> No | AA21: =IF(OR(J21<$AH$4,J21>$AH$5),"Sí","No") -> No
A22: TXN021 | B22: 45348 | C22: Norte | D22: Online | E22: Tablets | F22: Surface Pro 9 | G22: Ana García | H22: 395 | I22: 2 | J22: 750.5 | K22: 269.11 | L22: 239.2 | M22: 4 | N22: 7 | O22: 0.05 | P22: Efectivo | Q22: =L22/J22 -> 0.31872085 | R22: =IF(M22>4.5,"Premium",IF(M22>4,"Estandar","Riesgo")) -> Riesgo | S22: ="Q"&ROUNDUP(MONTH(B22)/3,0) -> Q1 | T22: =WEEKDAY(B22) -> 2 | U22: =IF(N22<=2,"Excelente",IF(N22<=4,"Buena","Mejorable")) -> Mejorable | V22: =VLOOKUP(G22,Datos_Empleados!B:E,4,FALSE) -> 37 | W22: =VLOOKUP(G22,Datos_Empleados!B:I,8,FALSE) -> 3.6 | X22: =INDEX(Datos_Productos!G:G,MATCH(F22,Datos_Productos!B:B,0)) -> 37 | Y22: =(J22-AVERAGE($J$2:$J$101))/_xlfn.STDEV.S($J$2:$J$101) -> -1.277582 | Z22: =IF(ABS(Y22)>2.5,"Sí","No") -> No | AA22: =IF(OR(J22<$AH$4,J22>$AH$5),"Sí","No") -> No
A23: TXN022 | B23: 45299 | C23: Sur | D23: Tienda | E23: Laptops | F23: Business Y2 | G23: Laura Sánchez | H23: 1265 | I23: 3 | J23: 3225.75 | K23: 935.24 | L23: 840.89 | M23: 4.5 | N23: 7 | O23: 0.15 | P23: Transferencia | Q23: =L23/J23 -> 0.26068046 | R23: =IF(M23>4.5,"Premium",IF(M23>4,"Estandar","Riesgo")) -> Estandar | S23: ="Q"&ROUNDUP(MONTH(B23)/3,0) -> Q1 | T23: =WEEKDAY(B23) -> 2 | U23: =IF(N23<=2,"Excelente",IF(N23<=4,"Buena","Mejorable")) -> Mejorable | V23: =VLOOKUP(G23,Datos_Empleados!B:E,4,FALSE) -> 33 | W23: =VLOOKUP(G23,Datos_Empleados!B:I,8,FALSE) -> 4.1 | X23: =INDEX(Datos_Productos!G:G,MATCH(F23,Datos_Productos!B:B,0)) -> 41 | Y23: =(J23-AVERAGE($J$2:$J$101))/_xlfn.STDEV.S($J$2:$J$101) -> 0.47460114 | Z23: =IF(ABS(Y23)>2.5,"Sí","No") -> No | AA23: =IF(OR(J23<$AH$4,J23>$AH$5),"Sí","No") -> No
A24: TXN023 | B24: 45376 | C24: Oeste | D24: Online | E24: Laptops | F24: Business Y2 | G24: José Martín | H24: 859 | I24: 5 | J24: 4295 | K24: 643.9 | L24: 1075.49 | M24: 3.1 | N24: 5 | O24: 0 | P24: Efectivo | Q24: =L24/J24 -> 0.25040512 | R24: =IF(M24>4.5,"Premium",IF(M24>4,"Estandar","Riesgo")) -> Riesgo | S24: ="Q"&ROUNDUP(MONTH(B24)/3,0) -> Q1 | T24: =WEEKDAY(B24) -> 2 | U24: =IF(N24<=2,"Excelente",IF(N24<=4,"Buena","Mejorable")) -> Mejorable | V24: =VLOOKUP(G24,Datos_Empleados!B:E,4,FALSE) -> 12 | W24: =VLOOKUP(G24,Datos_Empleados!B:I,8,FALSE) -> 4.5 | X24: =INDEX(Datos_Productos!G:G,MATCH(F24,Datos_Productos!B:B,0)) -> 41 | Y24: =(J24-AVERAGE($J$2:$J$101))/_xlfn.STDEV.S($J$2:$J$101) -> 1.2315032 | Z24: =IF(ABS(Y24)>2.5,"Sí","No") -> No | AA24: =IF(OR(J24<$AH$4,J24>$AH$5),"Sí","No") -> No
A25: TXN024 | B25: 45356 | C25: Sur | D25: Online | E25: Tablets | F25: iPad Air | G25: María Rodríguez | H25: 370 | I25: 5 | J25: 1850 | K25: 271.97 | L25: 490.17 | M25: 3.5 | N25: 1 | O25: 0 | P25: Transferencia | Q25: =L25/J25 -> 0.26495676 | R25: =IF(M25>4.5,"Premium",IF(M25>4,"Estandar","Riesgo")) -> Riesgo | S25: ="Q"&ROUNDUP(MONTH(B25)/3,0) -> Q1 | T25: =WEEKDAY(B25) -> 3 | U25: =IF(N25<=2,"Excelente",IF(N25<=4,"Buena","Mejorable")) -> Excelente | V25: =VLOOKUP(G25,Datos_Empleados!B:E,4,FALSE) -> 30 | W25: =VLOOKUP(G25,Datos_Empleados!B:I,8,FALSE) -> 4.2 | X25: =INDEX(Datos_Productos!G:G,MATCH(F25,Datos_Productos!B:B,0)) -> 38 | Y25: =(J25-AVERAGE($J$2:$J$101))/_xlfn.STDEV.S($J$2:$J$101) -> -0.49926656 | Z25: =IF(ABS(Y25)>2.5,"Sí","No") -> No | AA25: =IF(OR(J25<$AH$4,J25>$AH$5),"Sí","No") -> No
A26: TXN025 | B26: 45323 | C26: Norte | D26: Distribuidor | E26: Laptops | F26: Business Y2 | G26: Pedro González | H26: 1067 | I26: 2 | J26: 1920.6 | K26: 691.14 | L26: 676.56 | M26: 3.8 | N26: 6 | O26: 0.1 | P26: Transferencia | Q26: =L26/J26 -> 0.35226492 | R26: =IF(M26>4.5,"Premium",IF(M26>4,"Estandar","Riesgo")) -> Riesgo | S26: ="Q"&ROUNDUP(MONTH(B26)/3,0) -> Q1 | T26: =WEEKDAY(B26) -> 5 | U26: =IF(N26<=2,"Excelente",IF(N26<=4,"Buena","Mejorable")) -> Mejorable | V26: =VLOOKUP(G26,Datos_Empleados!B:E,4,FALSE) -> 32 | W26: =VLOOKUP(G26,Datos_Empleados!B:I,8,FALSE) -> 4 | X26: =INDEX(Datos_Productos!G:G,MATCH(F26,Datos_Productos!B:B,0)) -> 41 | Y26: =(J26-AVERAGE($J$2:$J$101))/_xlfn.STDEV.S($J$2:$J$101) -> -0.44929014 | Z26: =IF(ABS(Y26)>2.5,"Sí","No") -> No | AA26: =IF(OR(J26<$AH$4,J26>$AH$5),"Sí","No") -> No
A27: TXN026 | B27: 45330 | C27: Oeste | D27: Tienda | E27: Laptops | F27: Gaming Pro X1 | G27: Miguel Torres | H27: 1376 | I27: 1 | J27: 1376 | K27: 973.56 | L27: 402.44 | M27: 4 | N27: 2 | O27: 0 | P27: Efectivo | Q27: =L27/J27 -> 0.29247093 | R27: =IF(M27>4.5,"Premium",IF(M27>4,"Estandar","Riesgo")) -> Riesgo | S27: ="Q"&ROUNDUP(MONTH(B27)/3,0) -> Q1 | T27: =WEEKDAY(B27) -> 5 | U27: =IF(N27<=2,"Excelente",IF(N27<=4,"Buena","Mejorable")) -> Excelente | V27: =VLOOKUP(G27,Datos_Empleados!B:E,4,FALSE) -> 12 | W27: =VLOOKUP(G27,Datos_Empleados!B:I,8,FALSE) -> 4.3 | X27: =INDEX(Datos_Productos!G:G,MATCH(F27,Datos_Productos!B:B,0)) -> 41 | Y27: =(J27-AVERAGE($J$2:$J$101))/_xlfn.STDEV.S($J$2:$J$101) -> -0.83480229 | Z27: =IF(ABS(Y27)>2.5,"Sí","No") -> No | AA27: =IF(OR(J27<$AH$4,J27>$AH$5),"Sí","No") -> No
A28: TXN027 | B28: 45300 | C28: Sur | D28: Tienda | E28: Smartphones | F28: iPhone 15 Pro | G28: Miguel Torres | H28: 1156 | I28: 3 | J28: 3468 | K28: 848.01 | L28: 923.97 | M28: 4.1 | N28: 6 | O28: 0 | P28: Tarjeta | Q28: =L28/J28 -> 0.26642734 | R28: =IF(M28>4.5,"Premium",IF(M28>4,"Estandar","Riesgo")) -> Estandar | S28: ="Q"&ROUNDUP(MONTH(B28)/3,0) -> Q1 | T28: =WEEKDAY(B28) -> 3 | U28: =IF(N28<=2,"Excelente",IF(N28<=4,"Buena","Mejorable")) -> Mejorable | V28: =VLOOKUP(G28,Datos_Empleados!B:E,4,FALSE) -> 12 | W28: =VLOOKUP(G28,Datos_Empleados!B:I,8,FALSE) -> 4.3 | X28: =INDEX(Datos_Productos!G:G,MATCH(F28,Datos_Productos!B:B,0)) -> 38 | Y28: =(J28-AVERAGE($J$2:$J$101))/_xlfn.STDEV.S($J$2:$J$101) -> 0.64608539 | Z28: =IF(ABS(Y28)>2.5,"Sí","No") -> No | AA28: =IF(OR(J28<$AH$4,J28>$AH$5),"Sí","No") -> No
A29: TXN028 | B29: 45309 | C29: Este | D29: Online | E29: Laptops | F29: UltraBook Z3 | G29: María Rodríguez | H29: 1078 | I29: 3 | J29: 3072.3 | K29: 801.52 | L29: 787.98 | M29: 3.4 | N29: 6 | O29: 0.05 | P29: Efectivo | Q29: =L29/J29 -> 0.25647886 | R29: =IF(M29>4.5,"Premium",IF(M29>4,"Estandar","Riesgo")) -> Riesgo | S29: ="Q"&ROUNDUP(MONTH(B29)/3,0) -> Q1 | T29: =WEEKDAY(B29) -> 5 | U29: =IF(N29<=2,"Excelente",IF(N29<=4,"Buena","Mejorable")) -> Mejorable | V29: =VLOOKUP(G29,Datos_Empleados!B:E,4,FALSE) -> 30 | W29: =VLOOKUP(G29,Datos_Empleados!B:I,8,FALSE) -> 4.2 | X29: =INDEX(Datos_Productos!G:G,MATCH(F29,Datos_Productos!B:B,0)) -> 29 | Y29: =(J29-AVERAGE($J$2:$J$101))/_xlfn.STDEV.S($J$2:$J$101) -> 0.36597676 | Z29: =IF(ABS(Y29)>2.5,"Sí","No") -> No | AA29: =IF(OR(J29<$AH$4,J29>$AH$5),"Sí","No") -> No
... A101: TXN100 | B101: 45370 | C101: Norte | D101: Distribuidor | E101: Tablets | F101: Surface Pro 9 | G101: Laura Sánchez | H101: 769 | I101: 1 | J101: 769 | K101: 614.98 | L101: 154.02 | M101: 4.7 | N101: 4 | O101: 0 | P101: Transferencia | Q101: =L101/J101 -> 0.20028609 | R101: =IF(M101>4.5,"Premium",IF(M101>4,"Estandar","Riesgo")) -> Premium | S101: ="Q"&ROUNDUP(MONTH(B101)/3,0) -> Q1 | T101: =WEEKDAY(B101) -> 3 | U101: =IF(N101<=2,"Excelente",IF(N101<=4,"Buena","Mejorable")) -> Buena | V101: =VLOOKUP(G101,Datos_Empleados!B:E,4,FALSE) -> 33 | W101: =VLOOKUP(G101,Datos_Empleados!B:I,8,FALSE) -> 4.1 | X101: =INDEX(Datos_Productos!G:G,MATCH(F101,Datos_Productos!B:B,0)) -> 37 | Y101: =(J101-AVERAGE($J$2:$J$101))/_xlfn.STDEV.S($J$2:$J$101) -> -1.2644862 | Z101: =IF(ABS(Y101)>2.5,"Sí","No") -> No | AA101: =IF(OR(J101<$AH$4,J101>$AH$5),"Sí","No") -> No

Sheet Datos_Empleados
A1: ID_Empleado | B1: Nombre | C1: Region | D1: Puesto | E1: Antiguedad_Meses | F1: Ventas_Objetivo | G1: Ventas_Reales | H1: Comision_Pct | I1: Satisfaccion_Laboral | J1: Capacitaciones_Completadas
A2: EMP001 | B2: Ana García | C2: Norte | D2: Vendedor Senior | E2: 37 | F2: 54534 | G2: 45230.3 | H2: 0.08 | I2: 3.6 | J2: 12
A3: EMP002 | B3: Carlos López | C3: Sur | D3: Vendedor | E3: 10 | F3: 44135 | G3: 40163.13 | H3: 0.06 | I3: 4.4 | J3: 11
A4: EMP003 | B4: María Rodríguez | C4: Este | D4: Vendedor Senior | E4: 30 | F4: 59575 | G4: 60303.17 | H4: 0.08 | I4: 4.2 | J4: 12
A5: EMP004 | B5: José Martín | C5: Oeste | D5: Vendedor | E5: 12 | F5: 43749 | G5: 49922.73 | H5: 0.06 | I5: 4.5 | J5: 15
A6: EMP005 | B6: Laura Sánchez | C6: Sur | D6: Vendedor Senior | E6: 33 | F6: 54796 | G6: 63302.33 | H6: 0.08 | I6: 4.1 | J6: 10
A7: EMP006 | B7: Pedro González | C7: Oeste | D7: Vendedor Senior | E7: 32 | F7: 43115 | G7: 39882.21 | H7: 0.08 | I7: 4 | J7: 7
A8: EMP007 | B8: Carmen Ruiz | C8: Este | D8: Vendedor | E8: 15 | F8: 55540 | G8: 45923.43 | H8: 0.06 | I8: 4.7 | J8: 4
A9: EMP008 | B9: Miguel Torres | C9: Oeste | D9: Vendedor | E9: 12 | F9: 52210 | G9: 58720.99 | H9: 0.06 | I9: 4.3 | J9: 12

Sheet Datos_Productos
A1: Codigo_Producto | B1: Nombre_Producto | C1: Categoria | D1: Precio_Lista | E1: Costo_Produccion | F1: Margen_Objetivo | G1: Stock_Actual | H1: Proveedor | I1: Tiempo_Reposicion
A2: PROD001 | B2: Gaming Pro X1 | C2: Laptops | D2: 1287 | E2: 908.84 | F2: 0.294 | G2: 41 | H2: TechSupply Inc | I2: 6
A3: PROD002 | B3: Business Y2 | C3: Laptops | D3: 1210 | E3: 829.29 | F3: 0.315 | G3: 41 | H3: TechSupply Inc | I3: 11
A4: PROD003 | B4: UltraBook Z3 | C4: Laptops | D4: 1369 | E4: 896.89 | F4: 0.345 | G4: 29 | H4: TechSupply Inc | I4: 14
A5: PROD004 | B5: iPhone 15 Pro | C5: Smartphones | D5: 959 | E5: 657.07 | F5: 0.315 | G5: 38 | H5: Mobile Direct | I5: 13
A6: PROD005 | B6: Galaxy S24 | C6: Smartphones | D6: 908 | E6: 604.25 | F6: 0.335 | G6: 35 | H6: Mobile Direct | I6: 8
A7: PROD006 | B7: Pixel 8 Pro | C7: Smartphones | D7: 855 | E7: 585.68 | F7: 0.315 | G7: 37 | H7: Mobile Direct | I7: 10
A8: PROD007 | B8: iPad Air | C8: Tablets | D8: 458 | E8: 332.63 | F8: 0.274 | G8: 38 | H8: Tablet Corp | I8: 8
A9: PROD008 | B9: Galaxy Tab S9 | C9: Tablets | D9: 619 | E9: 454.67 | F9: 0.265 | G9: 44 | H9: Tablet Corp | I9: 14
A10: PROD009 | B10: Surface Pro 9 | C10: Tablets | D10: 714 | E10: 512.29 | F10: 0.283 | G10: 37 | H10: Tablet Corp | I10: 5

Sheet Datos_Marketing
A1: Fecha | B1: Region | C1: Canal_Marketing | D1: Inversion | E1: Impresiones | F1: Clicks | G1: Conversiones | H1: Costo_Por_Click | I1: ROI
A2: 45292 | B2: Norte | C2: Google Ads | D2: 6988 | E2: 174700 | F2: 7841 | G2: 340 | H2: 0.89 | I2: 1.43
A3: 45292 | B3: Norte | C3: Facebook Ads | D3: 3477 | E3: 66063 | F3: 2713 | G3: 123 | H3: 1.28 | I3: 0.77
A4: 45292 | B4: Norte | C4: LinkedIn Ads | D4: 4783 | E4: 95660 | F4: 1930 | G4: 141 | H4: 2.48 | I4: 0.47
A5: 45292 | B5: Norte | C5: Email Marketing | D5: 6639 | E5: 165975 | F5: 5315 | G5: 197 | H5: 1.25 | I5: 0.48
A6: 45292 | B6: Sur | C6: Google Ads | D6: 7186 | E6: 107790 | F6: 2452 | G6: 138 | H6: 2.93 | I6: -0.04
A7: 45292 | B7: Sur | C7: Facebook Ads | D7: 5081 | E7: 106701 | F7: 3586 | G7: 135 | H7: 1.42 | I7: 0.33
A8: 45292 | B8: Sur | C8: LinkedIn Ads | D8: 4552 | E8: 91040 | F8: 3942 | G8: 230 | H8: 1.15 | I8: 1.53
A9: 45292 | B9: Sur | C9: Email Marketing | D9: 2695 | E9: 40425 | F9: 997 | G9: 67 | H9: 2.7 | I9: 0.24
A10: 45292 | B10: Este | C10: Google Ads | D10: 2407 | E10: 60175 | F10: 1350 | G10: 70 | H10: 1.78 | I10: 0.45
A11: 45292 | B11: Este | C11: Facebook Ads | D11: 5473 | E11: 120406 | F11: 4600 | G11: 233 | H11: 1.19 | I11: 1.13
A12: 45292 | B12: Este | C12: LinkedIn Ads | D12: 3765 | E12: 86595 | F12: 2027 | G12: 104 | H12: 1.86 | I12: 0.38
A13: 45292 | B13: Este | C13: Email Marketing | D13: 4320 | E13: 108000 | F13: 4358 | G13: 236 | H13: 0.99 | I13: 1.73
... A49: 45352 | B49: Oeste | C49: Email Marketing | D49: 2774 | E49: 63802 | F49: 2574 | G49: 113 | H49: 1.08 | I49: 1.04

Sheet Criterios_Analisis
A1: Region | B1: Ingresos_Totales | D1: Satisfaccion_Cliente | E1: Tiempo_Entrega
A2: Norte | B2: >2000 | D2: <4 | E2: >4

Sheet Estadisticas_Descriptivas
A1: Region | B1: N | C1: Media_Ingresos | D1: Mediana_Ingresos | E1: Desv_Est | F1: CV | G1: Q1 | H1: Q3 | I1: IQR
A2: Norte | B2: =COUNTIF(Datos_Ventas_Completos!C:C,"Norte") -> 26 | C2: =AVERAGEIF(Datos_Ventas_Completos!C:C,"Norte",Datos_Ventas_Completos!J:J) -> 2464.8077 | D2: {=MEDIAN(_xlfn._xlws.FILTER(Datos_Ventas_Completos!J:J,Datos_Ventas_Completos!C:C="Norte"))} -> 2349.6 | E2: {=_xlfn.STDEV.S(_xlfn._xlws.FILTER(Datos_Ventas_Completos!J:J,Datos_Ventas_Completos!C:C="Norte"))} -> 1526.4099 | F2: =E2/C2 -> 0.61928156 | G2: {=_xlfn.QUARTILE.INC(_xlfn._xlws.FILTER(Datos_Ventas_Completos!J:J,Datos_Ventas_Completos!C:C="Norte"),1)} -> 1137 | H2: {=_xlfn.QUARTILE.INC(_xlfn._xlws.FILTER(Datos_Ventas_Completos!J:J,Datos_Ventas_Completos!C:C="Norte"),3)} -> 3409.3875 | I2: =H2-G2 -> 2272.3875
A3: Sur | B3: =COUNTIF(Datos_Ventas_Completos!C:C,"Sur") -> 24 | C3: =AVERAGEIF(Datos_Ventas_Completos!C:C,"sUR",Datos_Ventas_Completos!J:J) -> 2430.9375 | D3: {=MEDIAN(_xlfn._xlws.FILTER(Datos_Ventas_Completos!J:J,Datos_Ventas_Completos!C:C="Sur"))} -> 1879 | E3: {=_xlfn.STDEV.S(_xlfn._xlws.FILTER(Datos_Ventas_Completos!J:J,Datos_Ventas_Completos!C:C="Sur"))} -> 1483.5342 | F3: =E3/C3 -> 0.61027245 | G3: {=_xlfn.QUARTILE.INC(_xlfn._xlws.FILTER(Datos_Ventas_Completos!J:J,Datos_Ventas_Completos!C:C="Sur"),1)} -> 1326.3625 | H3: {=_xlfn.QUARTILE.INC(_xlfn._xlws.FILTER(Datos_Ventas_Completos!J:J,Datos_Ventas_Completos!C:C="Sur"),3)} -> 3503 | I3: =H3-G3 -> 2176.6375
A4: Este | B4: =COUNTIF(Datos_Ventas_Completos!C:C,"Este") -> 22 | C4: =AVERAGEIF(Datos_Ventas_Completos!C:C,"Este",Datos_Ventas_Completos!J:J) -> 2615.6614 | D4: {=MEDIAN(_xlfn._xlws.FILTER(Datos_Ventas_Completos!J:J,Datos_Ventas_Completos!C:C="Este"))} -> 2615.4 | E4: {=_xlfn.STDEV.S(_xlfn._xlws.FILTER(Datos_Ventas_Completos!J:J,Datos_Ventas_Completos!C:C="Este"))} -> 1292.0817 | F4: =E4/C4 -> 0.49397898 | G4: {=_xlfn.QUARTILE.INC(_xlfn._xlws.FILTER(Datos_Ventas_Completos!J:J,Datos_Ventas_Completos!C:C="Este"),1)} -> 1678.65 | H4: {=_xlfn.QUARTILE.INC(_xlfn._xlws.FILTER(Datos_Ventas_Completos!J:J,Datos_Ventas_Completos!C:C="Este"),3)} -> 3298.575 | I4: =H4-G4 -> 1619.925
A5: Oeste | B5: =COUNTIF(Datos_Ventas_Completos!C:C,"Oeste") -> 28 | C5: =AVERAGEIF(Datos_Ventas_Completos!C:C,"Oeste",Datos_Ventas_Completos!J:J) -> 2698.4875 | D5: {=MEDIAN(_xlfn._xlws.FILTER(Datos_Ventas_Completos!J:J,Datos_Ventas_Completos!C:C="Oeste"))} -> 2767.5 | E5: {=_xlfn.STDEV.S(_xlfn._xlws.FILTER(Datos_Ventas_Completos!J:J,Datos_Ventas_Completos!C:C="Oeste"))} -> 1393.123 | F5: =E5/C5 -> 0.51626068 | G5: {=_xlfn.QUARTILE.INC(_xlfn._xlws.FILTER(Datos_Ventas_Completos!J:J,Datos_Ventas_Completos!C:C="Oeste"),1)} -> 1726.4 | H5: {=_xlfn.QUARTILE.INC(_xlfn._xlws.FILTER(Datos_Ventas_Completos!J:J,Datos_Ventas_Completos!C:C="Oeste"),3)} -> 3393.8 | I5: =H5-G5 -> 1667.4
A7: MATRIZ DE CORRELACIONES
B8: Ingresos_Totales | C8: Satisfaccion_Cliente | D8: Tiempo_Entrega | E8: Precio_Unitario | F8: Cantidad | G8: Descuento_Aplicado
A9: Ingresos_Totales | B9: =CORREL(Datos_Ventas_Completos!J:J,Datos_Ventas_Completos!J:J) -> 1 | C9: =CORREL(Datos_Ventas_Completos!J:J,Datos_Ventas_Completos!M:M) -> -0.13513512 | D9: =CORREL(Datos_Ventas_Completos!J:J,Datos_Ventas_Completos!N:N) -> -0.018760845 | E9: =CORREL(Datos_Ventas_Completos!J:J,Datos_Ventas_Completos!H:H) -> 0.57372858 | F9: =CORREL(Datos_Ventas_Completos!J:J,Datos_Ventas_Completos!I:I) -> 0.75392663 | G9: =CORREL(Datos_Ventas_Completos!J:J,Datos_Ventas_Completos!O:O) -> -0.053873173
A10: Satisfaccion_Cliente | B10: =CORREL(Datos_Ventas_Completos!M:M,Datos_Ventas_Completos!J:J) -> -0.13513512 | C10: =CORREL(Datos_Ventas_Completos!M:M,Datos_Ventas_Completos!M:M) -> 1 | D10: =CORREL(Datos_Ventas_Completos!M:M,Datos_Ventas_Completos!N:N) -> -0.055356741 | E10: =CORREL(Datos_Ventas_Completos!M:M,Datos_Ventas_Completos!H:H) -> 0.0056402918 | F10: =CORREL(Datos_Ventas_Completos!M:M,Datos_Ventas_Completos!I:I) -> -0.17440222 | G10: =CORREL(Datos_Ventas_Completos!M:M,Datos_Ventas_Completos!O:O) -> 0.027019816
A11: Tiempo_Entrega | B11: =CORREL(Datos_Ventas_Completos!N:N,Datos_Ventas_Completos!J:J) -> -0.018760845 | C11: =CORREL(Datos_Ventas_Completos!N:N,Datos_Ventas_Completos!M:M) -> -0.055356741 | D11: =CORREL(Datos_Ventas_Completos!N:N,Datos_Ventas_Completos!N:N) -> 1 | E11: =CORREL(Datos_Ventas_Completos!N:N,Datos_Ventas_Completos!H:H) -> -0.014948044 | F11: =CORREL(Datos_Ventas_Completos!N:N,Datos_Ventas_Completos!I:I) -> -0.034115889 | G11: =CORREL(Datos_Ventas_Completos!N:N,Datos_Ventas_Completos!O:O) -> 0.069221009
A12: Precio_Unitario | B12: =CORREL(Datos_Ventas_Completos!H:H,Datos_Ventas_Completos!J:J) -> 0.57372858 | C12: =CORREL(Datos_Ventas_Completos!H:H,Datos_Ventas_Completos!M:M) -> 0.0056402918 | D12: =CORREL(Datos_Ventas_Completos!H:H,Datos_Ventas_Completos!N:N) -> -0.014948044 | E12: =CORREL(Datos_Ventas_Completos!H:H,Datos_Ventas_Completos!H:H) -> 1 | F12: =CORREL(Datos_Ventas_Completos!H:H,Datos_Ventas_Completos!I:I) -> -0.035293579 | G12: =CORREL(Datos_Ventas_Completos!H:H,Datos_Ventas_Completos!O:O) -> 0.16840811
A13: Cantidad | B13: =CORREL(Datos_Ventas_Completos!I:I,Datos_Ventas_Completos!J:J) -> 0.75392663 | C13: =CORREL(Datos_Ventas_Completos!I:I,Datos_Ventas_Completos!M:M) -> -0.17440222 | D13: =CORREL(Datos_Ventas_Completos!I:I,Datos_Ventas_Completos!N:N) -> -0.034115889 | E13: =CORREL(Datos_Ventas_Completos!I:I,Datos_Ventas_Completos!H:H) -> -0.035293579 | F13: =CORREL(Datos_Ventas_Completos!I:I,Datos_Ventas_Completos!I:I) -> 1 | G13: =CORREL(Datos_Ventas_Completos!I:I,Datos_Ventas_Completos!O:O) -> -0.051514358
A14: Descuento_Aplicado | B14: =CORREL(Datos_Ventas_Completos!O:O,Datos_Ventas_Completos!J:J) -> -0.053873173 | C14: =CORREL(Datos_Ventas_Completos!O:O,Datos_Ventas_Completos!M:M) -> 0.027019816 | D14: =CORREL(Datos_Ventas_Completos!O:O,Datos_Ventas_Completos!N:N) -> 0.069221009 | E14: =CORREL(Datos_Ventas_Completos!O:O,Datos_Ventas_Completos!H:H) -> 0.16840811 | F14: =CORREL(Datos_Ventas_Completos!O:O,Datos_Ventas_Completos!I:I) -> -0.051514358 | G14: =CORREL(Datos_Ventas_Completos!O:O,Datos_Ventas_Completos!O:O) -> 1
A17: Variable 1 | B17: Variable 2 | C17: Correlación | D17: Tipo | E17: Interpretación | F17: ¿Espuria?
A18: Ingresos_Totales | B18: Cantidad | C18: =B13 -> 0.75392663 | D18: Fuerte positiva | E18: A mayor cantidad vendida, mayores ingresos. | F18: No
A19: Precio_Unitario | B19: Cantidad | C19: =E13 -> -0.035293579 | D19: Muy débil negativa | E19: El precio no afecta significativamente la cantidad vendida. | F19: Sí
A20: Tiempo_Entrega | B20: Satisfaccion_Cliente | C20: =C11 -> -0.055356741 | D20: Débil negativa | E20: Mayor tiempo de entrega reduce ligeramente la satisfacción del cliente. | F20: No
A21: Ingresos_Totales | B21: Satisfaccion_Cliente | C21: =C9 -> -0.13513512 | D21: Débil negativa | E21: Mayores ingresos no implican mayor satisfacción del cliente. | F21: Posible

Sheet Distribuciones
B1: Ingresos_Totales
A2: Media | B2: =AVERAGE(Datos_Ventas_Completos!J:J) -> 2555.297
A3: Mediana | B3: =MEDIAN(Datos_Ventas_Completos!J:J) -> 2338.65
A4: Desviación estándar | B4: =_xlfn.STDEV.S(Datos_Ventas_Completos!J:J) -> 1412.6662
A5: Asimetría (SKEV) | B5: =SKEW(Datos_Ventas_Completos!J:J) -> 0.53223626
A6: Curtosis | B6: =KURT(Datos_Ventas_Completos!J:J) -> -0.36587386

Sheet Modelos_Regresion
A1: Resumen | K1: Resumen
N2: El modelo múltiple explica mucho mejor los ingresos que el modelo simple.
A3: Estadísticas de la regresión | D3: Con pendiente negativa a mayor satisfacción, los ingresos disminuyen ligeramente. | K3: Estadísticas de la regresión | N3: El modelo de regresión múltiple muestra una mejora significativa en el poder explicativo (R² ≈ 0.37). La variable más influyente es el descuento, seguido por la satisfacción del cliente. El efecto negativo del descuento sugiere que mayores descuentos reducen los ingresos, mientras que el precio tiene un impacto positivo.
A4: Coeficiente de correlación múltiple | B4: 0.13513512 | K4: Coeficiente de correlación múltiple | L4: 0.61298178 | N4: El modelo de regresión múltiple mejora significativamente la capacidad explicativa respecto al modelo simple. Se identifica que el descuento aplicado tiene el mayor impacto negativo en los ingresos, mientras que el precio unitario contribuye positivamente. La satisfacción del cliente presenta una relación negativa, lo cual puede indicar dinámicas particulares del negocio. En general, el modelo permite una mejor comprensión de los factores que influyen en los ingresos.
A5: Coeficiente de determinación R^2 | B5: 0.018261502 | C5: El modelo explica muy poco la variabilidad de los ingresos. | K5: Coeficiente de determinación R^2 | L5: 0.37574666 | N5: No se observan problemas graves de multicolinealidad, ya que las correlaciones entre variables independientes no son excesivamente altas.
A6: R^2 ajustado | B6: 0.0082437621 | K6: R^2 ajustado | L6: 0.3425417 | N6: El análisis de residuos no muestra patrones evidentes, lo que sugiere que el modelo cumple razonablemente con los supuestos de linealidad y homocedasticidad.
A7: Error típico | B7: 1406.8313 | K7: Error típico | L7: 1145.4435 | N7: Los residuos se distribuyen de forma aleatoria alrededor de cero, lo que indica un ajuste adecuado del modelo.
A8: Observaciones | B8: 100 | K8: Observaciones | L8: 100 | N8: La variable descuento aplicado es estadísticamente significativa, mientras que las demás variables presentan menor relevancia estadística dentro del modelo.
N9: Se identifican diferencias en los coeficientes entre regiones, lo que sugiere que los factores que influyen en los ingresos varían según el mercado. Esto permite desarrollar estrategias específicas por región.
A10: ANÁLISIS DE VARIANZA | K10: ANÁLISIS DE VARIANZA
B11: Grados de libertad | C11: Suma de cuadrados | D11: Promedio de los cuadrados | E11: F | F11: Valor crítico de F | L11: Grados de libertad | M11: Suma de cuadrados | N11: Promedio de los cuadrados | O11: F | P11: Valor crítico de F | R11: La elasticidad precio-demanda es negativa, lo que indica que al aumentar el precio, la cantidad demandada disminuye. La magnitud de la elasticidad sugiere que la demanda es (elástica/inelástica).
A12: Regresión | B12: 1 | C12: 3607869.4 | D12: 3607869.4 | E12: 1.8229164 | F12: 0.18007655 | K12: Regresión | L12: 5 | M12: 74235125 | N12: 14847025 | O12: 11.315978 | P12: 1.4731204e-08
A13: Residuos | B13: 98 | C13: 1.9395909e+08 | D13: 1979174.4 | K13: Residuos | L13: 94 | M13: 1.2333183e+08 | N13: 1312040.8
A14: Total | B14: 99 | C14: 1.9756696e+08 | K14: Total | L14: 99 | M14: 1.9756696e+08
B16: Coeficientes | C16: Error típico | D16: Estadístico t | E16: Probabilidad | F16: Inferior 95% | G16: Superior 95% | H16: Inferior 95.0% | I16: Superior 95.0% | L16: Coeficientes | M16: Error típico | N16: Estadístico t | O16: Probabilidad | P16: Inferior 95% | Q16: Superior 95% | R16: Inferior 95.0% | S16: Superior 95.0%
A17: Intercepción | B17: 3914.155 | C17: 1016.2314 | D17: 3.8516374 | E17: 0.00020942027 | F17: 1897.4768 | G17: 5930.8333 | H17: 1897.4768 | I17: 5930.8333 | K17: Intercepción | L17: 1485.0418 | M17: 962.52535 | N17: 1.5428599 | O17: 0.12622471 | P17: -426.07485 | Q17: 3396.1584 | R17: -426.07485 | S17: 3396.1584
A18: Satisfaccion_Cliente | B18: -340.48058 | C18: 252.17904 | D18: -1.3501542 | E18: 0.18007655 | F18: -840.92167 | G18: 159.9605 | H18: -840.92167 | I18: 159.9605 | K18: Precio_Unitario | L18: 2.8450608 | M18: 0.39057653 | N18: 7.2842594 | O18: 9.8311922e-11 | P18: 2.0695619 | Q18: 3.6205596 | R18: 2.0695619 | S18: 3.6205596
K19: Satisfaccion_Cliente | L19: -355.04115 | M19: 206.47295 | N19: -1.7195529 | O19: 0.08880488 | P19: -764.99803 | Q19: 54.915719 | R19: -764.99803 | S19: 54.915719
K20: Descuento_Aplicado | L20: -4229.3229 | M20: 2115.1248 | N20: -1.9995619 | O20: 0.048434269 | P20: -8428.9527 | Q20: -29.693081 | R20: -8428.9527 | S20: -29.693081
K21: Tiempo_Entrega | L21: -9.3813664 | M21: 56.540085 | N21: -0.16592417 | O21: 0.86857298 | P21: -121.64303 | Q21: 102.8803 | R21: -121.64303 | S21: 102.8803
A22: Análisis de los residuales | K22: Antigüedad_Vendedor | L22: 10.501309 | M22: 11.9042 | N22: 0.88215163 | O22: 0.37994509 | P22: -13.134759 | Q22: 34.137378 | R22: -13.134759 | S22: 34.137378
A24: Observación | B24: Pronóstico Ingresos_Totales | C24: Residuos
A25: 1 | B25: 2279.8482 | C25: -1223.8482
A26: 2 | B26: 2416.0404 | C26: 4168.9596 | K26: Análisis de los residuales
A27: 3 | B27: 2756.521 | C27: -1089.721
A28: 4 | B28: 2245.8001 | C28: -1336.3001 | K28: Observación | L28: Pronóstico Ingresos_Totales | M28: Residuos
A29: 5 | B29: 2211.7521 | C29: -1859.3021 | K29: 1 | L29: 1399.6707 | M29: -343.67068
A30: 6 | B30: 2722.473 | C30: -654.27297 | K30: 2 | L30: 3739.5333 | M30: 2845.4667
A31: 7 | B31: 2450.0885 | C31: 332.7115 | K31: 3 | L31: 1495.1116 | M31: 171.6884
A32: 8 | B32: 2245.8001 | C32: 1384.1999 | K32: 4 | L32: 2453.6732 | M32: -1544.1732
A33: 9 | B33: 2518.1846 | C33: -1433.2846 | K33: 5 | L33: 614.23357 | M33: -261.78357
A34: 10 | B34: 2790.5691 | C34: -1897.5691 | K34: 6 | L34: 2278.5357 | M34: -210.33572
A35: 11 | B35: 2824.6171 | C35: 598.38286 | K35: 7 | L35: 2002.797 | M35: 780.00303
A36: 12 | B36: 2381.9924 | C36: -1424.3924 | K36: 8 | L36: 3467.6174 | M36: 162.38263
A37: 13 | B37: 2347.9443 | C37: -1048.3443 | K37: 9 | L37: 1701.1877 | M37: -616.2877
A38: 14 | B38: 2518.1846 | C38: -290.18462 | K38: 10 | L38: 2923.7728 | M38: -2030.7728
A39: 15 | B39: 2484.1366 | C39: -32.536558 | K39: 11 | L39: 3674.2333 | M39: -251.23332
A40: 16 | B40: 2756.521 | C40: 1697.479 | K40: 12 | L40: 2759.7014 | M40: -1802.1014
... A124: 100 | B124: 2313.8963 | C124: -1544.8963 | K124: 96 | L124: 1008.7884 | M124: -8.4383815
K125: 97 | L125: 2732.768 | M125: 2022.232
K126: 98 | L126: 1391.5415 | M126: -493.79151
K127: 99 | L127: 3645.6773 | M127: 987.52271
K128: 100 | L128: 2313.2178 | M128: -1544.2178

Sheet Inferencia_Estadistica
A1: Norte | B1: Sur | C1: Este | D1: Oeste | F1: Análisis de varianza de un factor | Q1: Online | R1: Tienda | T1: Prueba t para dos muestras suponiendo varianzas desiguales | X1: Con_Descuento | Y1: Sin_Descuento | AA1: Prueba t para dos muestras suponiendo varianzas desiguales
A2: 1056 | B2: 1666.8 | C2: 352.45 | D2: 2068.2 | K2: Los intervalos de confianza por región muestran que los ingresos promedio se encuentran dentro de rangos similares, lo que refuerza el resultado del ANOVA al no evidenciar diferencias estadísticamente significativas entre regiones. | Q2: 4.8 | R2: 3.4 | X2: 1666.8 | Y2: 893
A3: 6585 | B3: 2782.8 | C3: 3630 | D3: 1084.9 | F3: RESUMEN | Q3: 4.4 | R3: 4.9 | U3: Online | V3: Tienda | X3: 909.5 | Y3: 3423 | AB3: Con_Descuento | AC3: Sin_Descuento
A4: 909.5 | B4: 4454 | C4: 957.6 | D4: 893 | F4: Grupos | G4: Cuenta | H4: Suma | I4: Promedio | J4: Varianza | K4: Desv | L4: Error | M4: t | N4: LI | O4: LS | Q4: 4.9 | R4: 3.5 | T4: Media | U4: 3.962069 | V4: 3.9151515 | X4: 2068.2 | Y4: 2228 | AA4: Media | AB4: 2304.085 | AC4: 2554.3077
A5: 3423 | B5: 1720 | C5: 1299.6 | D5: 4295 | F5: Norte | G5: 26 | H5: 64085 | I5: 2464.8077 | J5: 2329927.3 | K5: =SQRT(J5) -> 1526.4099 | L5: =K5/SQRT(G5) -> 299.35362 | M5: =TINV(0.05,G5-1) -> 2.0595386 | N5: =I5-(L5*M5) -> 1848.2774 | O5: =I5+(N5*M5) -> 6271.4062 | Q5: 4.5 | R5: 4.1 | T5: Varianza | U5: 0.29815271 | V5: 0.23445076 | X5: 1084.9 | Y5: 1376 | AA5: Varianza | AB5: 1810926.4 | AC5: 1852385.9
A6: 2451.6 | B6: 3225.75 | C6: 2228 | D6: 1376 | F6: Sur | G6: 24 | H6: 58342.5 | I6: 2430.9375 | J6: 2200873.7 | K6: =SQRT(J6) -> 1483.5342 | L6: =K6/SQRT(G6) -> 302.82515 | M6: =TINV(0.05,G6-1) -> 2.0686576 | N6: =I6-(L6*M6) -> 1804.4959 | O6: =I6+(N6*M6) -> 6163.8218 | Q6: 3.6 | R6: 3.3 | T6: Observaciones | U6: 29 | V6: 33 | X6: 3225.75 | Y6: 3468 | AA6: Observaciones | AB6: 20 | AC6: 13
A7: 4080 | B7: 1850 | C7: 5032 | D7: 1083 | F7: Este | G7: 22 | H7: 57544.55 | I7: 2615.6614 | J7: 1669475.2 | K7: =SQRT(J7) -> 1292.0817 | L7: =K7/SQRT(G7) -> 275.47275 | M7: =TINV(0.05,G7-1) -> 2.0796138 | N7: =I7-(L7*M7) -> 2042.7844 | O7: =I7+(N7*M7) -> 6863.8641 | Q7: 4 | R7: 3.2 | T7: Diferencia hipotética de las medias | U7: 0 | X7: 828.9 | Y7: 1083 | AA7: Diferencia hipotética de las medias | AB7: 0
A8: 750.5 | B8: 3468 | C8: 5126.2 | D8: 4760 | F8: Oeste | G8: 28 | H8: 75557.65 | I8: 2698.4875 | J8: 1940791.7 | K8: =SQRT(J8) -> 1393.123 | L8: =K8/SQRT(G8) -> 263.2755 | M8: =TINV(0.05,G8-1) -> 2.0518305 | N8: =I8-(L8*M8) -> 2158.2908 | O8: =I8+(N8*M8) -> 7126.9344 | Q8: 3.1 | R8: 4.1 | T8: Grados de libertad | U8: 56 | X8: 711 | Y8: 1630 | AA8: Grados de libertad | AB8: 26
A9: 1920.6 | B9: 1485 | C9: 3072.3 | D9: 2638.4 | F9: A pesar de no existir diferencias significativas, la región Oeste presenta el mayor ingreso promedio, seguida por la región Este. | Q9: 3.5 | R9: 4.5 | T9: Estadístico t | U9: 0.35582656 | X9: 4042.25 | Y9: 1380 | AA9: Estadístico t | AB9: -0.51833883
A10: 1630 | B10: 1908 | C10: 1288.2 | D10: 2361.3 | Q10: 3.4 | R10: 4 | T10: P(T<=t) una cola | U10: 0.36165371 | X10: 3271.8 | Y10: 2316 | AA10: P(T<=t) una cola | AB10: 0.30430265
A11: 1380 | B11: 828.9 | C11: 4182 | D11: 3515 | F11: ANÁLISIS DE VARIANZA | Q11: 3.8 | R11: 4.1 | T11: Valor crítico de t (una cola) | U11: 1.6725223 | X11: 4042.6 | Y11: 4410 | AA11: Valor crítico de t (una cola) | AB11: 1.7056179
A12: 711 | B12: 4042.6 | C12: 2138.4 | D12: 2712 | F12: Origen de las variaciones | G12: Suma de cuadrados | H12: Grados de libertad | I12: Promedio de los cuadrados | J12: F | K12: Probabilidad | L12: Valor crítico para F | Q12: 4.8 | R12: 3.3 | T12: P(T<=t) dos colas | U12: 0.72330742 | X12: 1102.45 | Y12: 5240 | AA12: P(T<=t) dos colas | AB12: 0.60860531
A13: 4042.25 | B13: 1102.45 | C13: 3271.8 | D13: 2080.8 | F13: Entre grupos | G13: 1238326.4 | H13: 3 | I13: 412775.47 | J13: 0.20183732 | K13: 0.89488793 | L13: 2.6993926 | Q13: 3.6 | R13: 4.1 | T13: Valor crítico de t (dos colas) | U13: 2.0032407 | X13: 2875.5 | Y13: 3608 | AA13: Valor crítico de t (dos colas) | AB13: 2.0555294
A14: 1912 | B14: 1716 | C14: 3524 | D14: 2893.4 | F14: Dentro de los grupos | G14: 1.9632863e+08 | H14: 96 | I14: 2045089.9 | Q14: 3.9 | R14: 4.6 | X14: 5027.75 | Y14: 2151
A15: 2875.5 | B15: 1401 | C15: 3307.5 | D15: 5208 | Q15: 3.7 | R15: 4.3 | T15: La prueba t indica que no existe una diferencia estadísticamente significativa en la satisfacción del cliente entre el canal online y la tienda física (p-value = 0.7233). | X15: 3307.5 | AA15: El análisis muestra que no existe una diferencia estadísticamente significativa en los ingresos entre las ventas con descuento y sin descuento (p-value = 0.6086). Sin embargo, se observa que en promedio los ingresos son mayores cuando no se aplican descuentos, lo que podría indicar un posible impacto negativo de los descuentos en los ingresos, aunque no es concluyente estadísticamente.
A16: 2316 | B16: 4410 | C16: 2104.2 | D16: 4375 | F16: Total | G16: 1.9756696e+08 | H16: 99 | Q16: 3.9 | R16: 3.4 | T16: El análisis integral muestra que no existen diferencias significativas en los ingresos entre regiones, lo que indica un desempeño homogéneo a nivel geográfico. Asimismo, no se encontraron diferencias significativas en la satisfacción del cliente entre el canal online y la tienda física, sugiriendo consistencia en la experiencia del cliente. Sin embargo, se identificaron variables clave como la cantidad y el precio unitario que impactan significativamente los ingresos, lo que permite orientar estrategias comerciales hacia la optimización de estos factores. | X16: 568.1 | AA16: El análisis integral revela que los ingresos presentan un comportamiento consistente entre regiones, sin diferencias estadísticamente significativas. Asimismo, la satisfacción del cliente se mantiene homogénea entre los canales online y tienda física. En cuanto al impacto de descuentos, no se encontró evidencia estadística suficiente para afirmar una diferencia en los ingresos; sin embargo, se observa una tendencia donde las ventas sin descuento generan mayores ingresos promedio. Finalmente, variables como la cantidad y el precio unitario muestran una influencia significativa en el desempeño, destacando su importancia en la estrategia comercial.
A17: 5027.75 | B17: 698.25 | C17: 814.5 | D17: 568.1 | Q17: 3.4 | R17: 3.2 | T17: Se recomienda enfocar los esfuerzos en optimizar variables operativas como el precio y la cantidad de ventas, ya que estas tienen un impacto significativo en los ingresos. Además, mantener la consistencia en la experiencia del cliente en todos los canales y regiones, aprovechando que no existen diferencias significativas, permite escalar estrategias comerciales de manera uniforme. Finalmente, se sugiere continuar monitoreando posibles valores atípicos y realizar análisis periódicos para detectar oportunidades de mejora. | X17: 698.25 | AA17: Se recomienda enfocar las estrategias comerciales en la optimización del volumen de ventas y la política de precios, dado su impacto directo en los ingresos. Además, mantener una estrategia homogénea entre regiones y canales resulta viable, ya que no se identificaron diferencias significativas. En relación con los descuentos, se sugiere utilizarlos de manera estratégica y controlada, evaluando su impacto en la rentabilidad, ya que podrían estar reduciendo los ingresos promedio sin generar beneficios claros.
A18: 2561.2 | B18: 2221.05 | C18: 1536.8 | D18: 3353.4 | F18: El análisis ANOVA muestra que no existen diferencias estadísticamente significativas en los ingresos entre las regiones (p-value = 0.8949). Esto indica que el desempeño es similar en todas las regiones. | Q18: 4.5 | R18: 3.9 | X18: 3353.4
A19: 3859 | B19: 3608 | C19: 2156 | D19: 2823 | Q19: 4.1 | R19: 3.7 | X19: 2221.05
A20: 1548 | B20: 906.3 | C20: 3040.95 | D20: 3029.4 | Q20: 4.6 | R20: 4.4 | X20: 1843.2
A21: 891.65 | B21: 6043.5 | C21: 2239.2 | D21: 5240 | Q21: 4.4 | R21: 3.8 | X21: 3232.8
A22: 2648.6 | B22: 2151 | C22: 2991.6 | D22: 2886 | Q22: 3.7 | R22: 4.3
A23: 3368.55 | B23: 1000.35 | C23: 3251.25 | D23: 2964 | Q23: 3.2 | R23: 4
A24: 675.9 | B24: 4755 | D24: 1041 | Q24: 3.9 | R24: 3.4
A25: 4309.2 | B25: 897.75 | D25: 407.15 | Q25: 4.7 | R25: 3.9
A26: 2383.2 | D26: 2192.4 | Q26: 3.7 | R26: 3.6
A27: 769 | D27: 1843.2 | Q27: 3.5 | R27: 4.8
D28: 3232.8 | Q28: 3.8 | R28: 3.5
D29: 4633.2 | Q29: 4.5 | R29: 4.1
Q30: 3 | R30: 4.6
R31: 3.9
R32: 4.4
R33: 3.5
R34: 3.4
W40: La distribución de los tiempos de entrega presenta una forma aproximadamente normal, lo que permite aplicar modelos probabilísticos basados en esta distribucipon.
W42: MEDIA | X42: =AVERAGE(Datos_Ventas_Completos!N2:N101) -> 4.32
W43: DESVIACION | X43: =_xlfn.STDEV.P(Datos_Ventas_Completos!N2:N101) -> 2.0439178
W44: PROBABILIDAD DE ENTREGAR EN 3 DÍAS | X44: =_xlfn.NORM.DIST(3,X42,X43,TRUE) -> 0.25919844
W46: Se calcularon probabilidades de entrega, utilizando la distribución normal, lo que permite estimar la probabilidad de cumplimiento en distintos tiempos de entrega

Sheet Dashboard_Ejecutivo
A1: KPIs principales
A3: Ingresos Totales | B3: =SUM(Datos_Ventas_Completos!J:J) -> 255529.7
A4: Satisfacción Promedio | B4: =AVERAGE(Datos_Ventas_Completos!M:M) -> 3.991
A5: Transacciones | B5: 100
A6: Margen promedio | B6: =AVERAGE(Datos_Ventas_Completos!Q:Q) -> 0.29932871
A9: ANÁLISIS POR REGIÓN
A10: Región | B10: Ingresos | C10: Transacciones | D10: Satisfacción | E10: Ticket Promedio
A11: Norte | B11: =SUMIF(Datos_Ventas_Completos!C:C,"Norte",Datos_Ventas_Completos!J:J) -> 64085 | C11: =COUNTIF(Datos_Ventas_Completos!C:C,"Norte") -> 26 | D11: =AVERAGEIF(Datos_Ventas_Completos!C:C,"Norte",Datos_Ventas_Completos!M:M) -> 4.0269231 | E11: =B11/C11 -> 2464.8077
A12: Sur | B12: =SUMIF(Datos_Ventas_Completos!C:C,"Sur",Datos_Ventas_Completos!J:J) -> 58342.5 | C12: =COUNTIF(Datos_Ventas_Completos!C:C,"Sur") -> 24 | D12: =AVERAGEIF(Datos_Ventas_Completos!C:C,"Sur",Datos_Ventas_Completos!M:M) -> 4.0375 | E12: =B12/C12 -> 2430.9375
A13: Este | B13: =SUMIF(Datos_Ventas_Completos!C:C,"Este",Datos_Ventas_Completos!J:J) -> 57544.55 | C13: =COUNTIF(Datos_Ventas_Completos!C:C,"Este") -> 22 | D13: =AVERAGEIF(Datos_Ventas_Completos!C:C,"Este",Datos_Ventas_Completos!M:M) -> 4.1363636 | E13: =B13/C13 -> 2615.6614
A14: Oeste | B14: =SUMIF(Datos_Ventas_Completos!C:C,"Oeste",Datos_Ventas_Completos!J:J) -> 75557.65 | C14: =COUNTIF(Datos_Ventas_Completos!C:C,"Oeste") -> 28 | D14: =AVERAGEIF(Datos_Ventas_Completos!C:C,"Oeste",Datos_Ventas_Completos!M:M) -> 3.8035714 | E14: =B14/C14 -> 2698.4875
A16: TOP 5 PRODUCTOS POR INGRESOS
A17: Producto | B17: Ingresos Totales | C17: Unidades Vendidas | F17: Etiquetas de fila | G17: Suma de Ingresos_Totales | H17: Suma de Cantidad
A18: Gaming Pro X1 | B18: 55745.45 | C18: 53 | F18: Galaxy Tab S9 | G18: 5201.15 | H18: 12
A19: UltraBook Z3 | B19: 42915.6 | C19: 40 | F19: iPad Air | G19: 18760.8 | H19: 39
A20: Business Y2 | B20: 33434.95 | C20: 32 | F20: Surface Pro 9 | G20: 27593.5 | H20: 46
A21: Pixel 8 Pro | B21: 28120.4 | C21: 34 | F21: Total general | G21: 51555.45 | H21: 97
A22: Surface Pro 9 | B22: 27593.5 | C22: 46
A24: Región | B24: Media | C24: LI | D24: LS
A25: Norte | B25: 2464.8077 | C25: 1848.2774 | D25: 6271.4062
A26: Sur | B26: 2430.9375 | C26: 1804.4959 | D26: 6163.8218
A27: Este | B27: 2615.6614 | C27: 2042.7844 | D27: 6863.8641
A28: Oeste | B28: 2698.4875 | C28: 2158.2908 | D28: 7126.9344
A31: Etiquetas de fila | B31: Suma de Ingresos_Totales
A32: ene | B32: 22749.9
A33: 01-ene | B33: 568.1
A34: 10-ene | B34: 3481.05
A35: 12-ene | B35: 1000.35
A36: 13-ene | B36: 1041
A37: 16-ene | B37: 3232.8
A38: 18-ene | B38: 675.9
A39: 20-ene | B39: 2893.4
A40: 22-ene | B40: 4226
A41: 27-ene | B41: 2638.4
A42: 28-ene | B42: 1084.9
A43: 30-ene | B43: 1908
... A63: Total general | B63: 51555.45
F68: Se observa una tendencia estable en los ingresos, con algunos picos en determinados días, lo que puede indicar campañas o eventos específicos.

Sheet Resumen_Ejecutivo
A1: SITUACIÓN ACTUAL
A3: La empresa presenta ingresos totales por $255,529.70 con un total de 100 transacciones realizadas.
A4: La satisfacción promedio del cliente es de 3.99 sobre 5, lo que indica una percepción generalmente positiva del servicio.
A6: Se observa que la región Oeste genera los mayores ingresos promedio, seguida por la región Este, lo que sugiere diferencias en desempeño comercial entre regiones.
A8: Fortalezas:
A9: Buen nivel de satisfacción del cliente
A10: Ingresos estables
A11: Ticket promedio consistente
A13: Áreas de oportunidad:
A14: Variabilidad en desempeño entre regiones
A15: Oportunidad de mejorar satisfacción en ciertas zonas
A17: HALLAZGOS CLAVE
... A41: El análisis muestra que el principal driver del negocio es el volumen de ventas, más que factores como satisfacción o tiempo de entrega.
A44: Ingresos Totales | B44: =SUM(Datos_Ventas_Completos!J:J) -> 255529.7
A45: Descuentos | B45: =SUM(Datos_Ventas_Completos!O:O) -> 6.35
A46: Ingreso Neto | B46: =B44*(1-6.35%) -> 239303.56

Sheet Metodología
A1: Descripción de los datos utilizados:
A2: Se analizaron datos de ventas empresariales que incluyen variables como ingresos totales, satisfacción del cliente, tiempo de entrega, precio unitario, cantidad vendida y descuentos aplicados, así como segmentación por región y canal de venta.
A4: Métodos estadísticos aplicados:
A5: Se utilizaron estadísticas descriptivas (media, mediana, desviación estándar), análisis de correlación, modelos de regresión simple y múltiple, pruebas de hipótesis (ANOVA y pruebas t), detección de valores atípicos mediante Z-Score e IQR, así como análisis de distribuciones y probabilidades.
A7: Supuestos y limitaciones:
A8: Se asume que los datos son representativos y que las relaciones entre variables son lineales. Las limitaciones incluyen posibles sesgos en los datos, tamaño de muestra limitado y la no consideración de variables externas como factores macroeconómicos.
A10: Interpretación de resultados:
A11: Los resultados permiten identificar patrones de comportamiento en ventas, relaciones entre variables clave y factores que impactan el desempeño comercial, facilitando la toma de decisiones estratégicas.

Sheet Glosiario
A1: Media: Promedio de los valores de un conjunto de datos.
A2: Mediana: Valor central de un conjunto ordenado.
A3: Desviación estándar: Mide la dispersión de los datos respecto a la media.
A4: Correlación: Indica la relación entre dos variables.
A5: Regresión: Modelo que permite predecir una variable en función de otras.
A6: ANOVA: Prueba estadística para comparar medias entre varios grupos.
A7: Valor p: Probabilidad de obtener resultados bajo la hipótesis nula.
A8: Outlier: Valor atípico que se aleja del comportamiento general.
A10: Guía de interpretación:
A11: Valores cercanos a 1 o -1 indican relaciones fuertes.
A12: Valores p menores a 0.05 indican significancia estadística.
A13: Los modelos predictivos permiten estimar resultados futuros con cierto nivel de confianza.

Sheet Presentacion
A1: RESUMEN EJECUTIVO | G1: HALLAZGOS
A9: METODOLOGÍA | G9: RECOMENDACIONES
D17: PRÓXIMOS PASOS
